Workbook
Name \: #REF!
Name \\: #REF!
Name \хз: #REF!
Name _1: #REF!
Name Excel_BuiltIn_Print_Area_1_1: #REF!
Name Excel_BuiltIn_Print_Area_20_1: #REF!
Name Excel_BuiltIn_Print_Area_4: #REF!
Name Excel_BuiltIn_Print_Area_5: #REF!
Name H: #REF!
Name kjhiu: #REF!
Name smet: #REF!
Name tlbLists: #REF!
Name TR10B: #REF!
Name TR10C: #REF!
Name TR10EXP: #REF!
Name TR10PSZ: #REF!
Name TR10S: #REF!
Name TR10ST: #REF!
Name TR10Y: #REF!
Name TR111S: #REF!
Name TR11B: #REF!
Name TR11PSZ: #REF!
Name TR11S: #REF!
Name TR11ST: #REF!
Name TR11Y: #REF!
Name TR12B: #REF!
Name TR12EXP: #REF!
Name TR12PSZ: #REF!
Name TR12S: #REF!
Name TR12ST: #REF!
Name TR12Y: #REF!
Name TR15B: #REF!
Name TR15EXP: #REF!
Name TR15PSZ: #REF!
Name TR15S: #REF!
Name TR15ST: #REF!
Name TR15Y: #REF!
Name TR1EXP: #REF!
Name TR20B: #REF!
Name TR20EXP: #REF!
Name TR20PSZ: #REF!
Name TR20S: #REF!
Name TR20ST: #REF!
Name TR20Y: #REF!
Name TR21Y: #REF!
Name TR23B: #REF!
Name TR23EXP: #REF!
Name TR23PSZ: #REF!
Name TR23S: #REF!
Name TR23ST: #REF!
Name TR23Y: #REF!
Name TR8B: #REF!
Name TR8EXP: #REF!
Name TR8PSZ: #REF!
Name TR8S: #REF!
Name TR8ST: #REF!
Name TR8Y: #REF!
Name TR9B: #REF!
Name TR9EXP: #REF!
Name TR9PSZ: #REF!

Sheet Прил. № 5 Ф1(1д) прот
M1: Приложение № 5 к приказу ФАС России от 16.12.2022 № 995/22
O3: Форма № 1 (1д)
A5: Протокол (Согласование) цены (прогнозной цены) единицы продукции и выбора вида цены
K7: Государственный заказчик / Заказчик:
K8: Процедура: | L8: Определение цены контракта
K10: Метод определения цены: | L10: Затратный
K11: Примечание:
A14: № п/п | B14: Полное наименование товара, работы, услуги, шифр | C14: Код ОКП/ ОКПД2 | D14: Код ЕКПС (при наличии) | E14: ФНН (при наличии) | F14: Единица измерения | G14: Техническая документация (ТУ, ТЗ, КД, ГОСТ, иное), орган и дата утверждения | H14: Календарный год или срок действия цены | J14: Цена, заявленная организацией- поставщиком (подрядчиком, исполнителем) (без НДС, руб.) | K14: Цена, предлагаемая отраслевым органом (без НДС, руб.) | L14: Цена, принятая государственным заказчиком / заказчиком (без НДС, руб.) | M14: Вид цены
H15: начало | I15: окончание | M15: Предложено организацией-поставщиком (подрядчиком, исполнителем) | N15: Предложено отраслевым органом | O15: Предложено государственным заказчиком / заказчиком
A16: 1 | B16: 2 | C16: 3 | D16: 4 | E16: 5 | F16: 6 | G16: 7 | H16: 8.1 | I16: 8.2 | J16: 9 | K16: 10 | L16: 11 | M16: 12 | N16: 13 | O16: 14
A17: 1 | B17: ТЕМА | C17: 72.19.29 | D17: - | E17: - | F17: СЧ ОКР | G17: Техническое задание № | H17: Дата подписания договора | I17: 01.03.2026 | J17: ='2д план кальк (2)'!K58 | K17: - | L17: - | M17: ориентировочная | N17: - | O17: -
K19: Начальник ОФЭиАУ НИОКР
B20: _____________________ _____________ | K20: _____________________ Н.О. Васецкая
B21: (подпись) (Ф.И.О.) | K21: (подпись) (Ф.И.О.)
B22: «____» __________________ 2026 г. | K22: «____» __________________ 2026 г.
B23: М.П.
K25: Проректор по научной работе
K26: _____________________ Ю.В. Фомин
K27: (подпись) (Ф.И.О.)
K28: «____» __________________ 2026 г.
K29: М.П.

Sheet 2д план кальк (2)
M1: Форма № 2д
A3: Плановая калькуляция затрат
A4: на 2026-2027 гг.
B6: Наименование товара, работы, услуги | D6: ТЕМА
B7: Код по ОКП/ОКПД2 (шифр)
B8: Код по ЕКПС (при наличии)
B9: ФНН (при наличии)
B10: Калькуляционная единица | D10: этап
D11: (штука, комплект, этап, единица работы (услуги), иное)
B12: Техническая документация | D12: Техническое задание №
D13: (ТУ, ТЗ, КД, ГОСТ, иное) орган и дата утверждения
M14: (руб.)
A15: № № строк | B15: Наименование статей калькуляции | C15: Стоимостная оценка затрат на производство в условиях первого года производства | E15: Затраты на производство в первом году производства | F15: Принято государствен-ным заказчиком / заказчиком | G15: 2027-ый год | K15: Предложено организацией-поставщиком (подрядчиком, исполнителем) | L15: Принято государствен-ным заказчиком / заказчиком | M15: Примечание
G16: стоимостная оценка затрат 2027-ого года в условиях первого года производства | H16: применяе-мый индекс цен | I16: затраты 2027-го года | J16: принято государствен-ным заказчиком / заказчиком
A19: 1 | B19: 2 | C19: 3 | E19: 4 | F19: 5 | G19: 6 | H19: 7 | I19: 8 | J19: 9 | K19: 10 | L19: 11 | M19: 12
A20: 0100 | B20: Материальные затраты - всего: | C20: 0 | E20: 0 | G20: 0 | H20: - | I20: 0 | K20: =I20+E20
B21: в том числе:
A22: 0101 | B22: приобретение сырья, материалов и вспомогательных материалов | C22: 0 | E22: 0 | G22: 0 | H22: - | I22: 0 | K22: =I22+E22
A23: 0102 | B23: приобретение полуфабрикатов | C23: 0 | E23: 0 | G23: 0 | H23: - | I23: 0 | K23: =I23+E23
A24: 0103 | B24: возвратные отходы | C24: 0 | E24: 0 | G24: 0 | H24: - | I24: 0 | K24: =I24+E24
A25: 0104 | B25: приобретение комплектующих изделий | C25: 0 | E25: 0 | G25: 0 | H25: - | I25: 0 | K25: =I25+E25
A26: 0105 | B26: оплата работ и услуг сторонних организаций производственного характера | C26: 0 | E26: 0 | G26: 0 | H26: - | I26: 0 | K26: =I26+E26
A27: 0106 | B27: транспортно-заготовительные затраты | C27: 0 | E27: 0 | G27: 0 | H27: - | I27: 0 | K27: =I27+E27
A28: 0107 | B28: топливо на технологические цели | C28: 0 | E28: 0 | G28: 0 | H28: - | I28: 0 | K28: =I28+E28
A29: 0108 | B29: энергия на технологические цели | C29: 0 | E29: 0 | G29: 0 | H29: - | I29: 0 | K29: =I29+E29
A30: 0109 | B30: тара и упаковка | C30: 0 | E30: 0 | G30: 0 | H30: - | I30: 0 | K30: =I30+E30
A31: 0110 | B31: затраты на изделия собственного производства | C31: 0 | E31: 0 | G31: 0 | H31: - | I31: 0 | K31: =I31+E31
A32: 0200 | B32: Затраты на оплату труда - всего: | C32: =C34+C35 | E32: =E34+E35 | G32: =G34+G35 | H32: - | I32: =I34+I35 | K32: =I32+E32
B33: в том числе:
A34: 0201 | B34: основная заработная плата | C34: =ROUND('22 (22д) свед. о норм_26'!D15*C59,2) | E34: ='9 (9д) ОЗП НИР(ОКР)'!H13 | G34: =ROUND('22 (22д) свед. о норм_26'!D15*G59,2) | H34: - | I34: ='9 (9д) ОЗП НИР(ОКР)'!H18 | K34: =I34+E34
A35: 0202 | B35: дополнительная заработная плата | C35: =ROUND(C34*0.086866,2) | E35: =ROUND(E34*0.086866,2) | G35: =ROUND(G34*0.086866,2) | H35: - | I35: =ROUND(I34*0.086866,2) | K35: =I35+E35
A36: 0300 | B36: Страховые взносы на обязательное социальное страхование | C36: =ROUND(C32*0.302,2) | E36: =ROUND(E32*0.302,2) | G36: =ROUND(G32*0.302,2) | H36: - | I36: =ROUND(I32*0.302,2) | K36: =I36+E36
A37: 0400 | B37: Затраты на подготовку и освоение производства - всего: | C37: 0 | E37: 0 | G37: 0 | H37: - | I37: 0 | K37: =I37+E37
B38: в том числе:
A39: 0401 | B39: пусковые затраты | C39: 0 | E39: 0 | G39: 0 | H39: - | I39: 0 | K39: =I39+E39
A40: 0402 | B40: затраты на подготовку и освоение новых видов продукции | C40: 0 | E40: 0 | G40: 0 | H40: - | I40: 0 | K40: =I40+E40
A41: 0500 | B41: Затраты на специальную технологическую оснастку | C41: 0 | E41: 0 | G41: 0 | I41: 0 | K41: =I41+E41
A42: 0600 | B42: Затраты на специальное оборудование для научных (экспериментальных) работ9 | C42: 0 | E42: 0 | G42: 0 | H42: - | I42: 0 | K42: =I42+E42
A43: 0700 | B43: Специальные затраты | C43: 0 | E43: 0 | G43: 0 | H43: - | I43: 0 | K43: =I43+E43
A44: 0800 | B44: Общепроизводственные затраты | C44: 0 | E44: 0 | G44: 0 | H44: - | I44: 0 | K44: =I44+E44
A45: 0900 | B45: Общехозяйственные затраты | C45: =ROUND(C34*0.32,2) | E45: =ROUNDUP(E34*0.32,2) | G45: =ROUND(G34*0.32,2) | H45: - | I45: =ROUNDUP(I34*0.32,2) | K45: =I45+E45
A46: 1000 | B46: Затраты на командировки | C46: 0 | E46: 0 | G46: 0 | H46: - | I46: 0 | K46: =I46+E46
A47: 1100 | B47: Прочие прямые затраты | C47: 0 | E47: 0 | G47: 0 | H47: - | I47: 0 | K47: =I47+E47
A48: 1200 | B48: Затраты по работам (услугам), выполняемым (оказываемым) сторонними организациями10 | C48: 0 | E48: 0 | G48: 0 | H48: - | I48: 0 | K48: =I48+E48
A49: 1300 | B49: Производственная себестоимость | C49: =C45+C36+C32 | E49: =E45+E36+E32 | G49: =G45+G36+G32 | H49: - | I49: =I45+I36+I32 | K49: =I49+E49
A50: 1400 | B50: Коммерческие (внепроизводственные) затраты | C50: 0 | E50: 0 | G50: 0 | H50: - | I50: 0 | K50: =I50+E50
A51: 1500 | B51: Проценты по кредитам11 | C51: 0 | E51: 0 | G51: 0 | I51: 0 | K51: =I51+E51
A52: 1600 | B52: Административно-управленческие расходы12 | C52: 0 | E52: 0 | G52: 0 | H52: - | I52: 0 | K52: =I52+E52
A53: 1700 | B53: Себестоимость продукции | C53: =C49 | E53: =E49 | G53: =G49 | H53: - | I53: =I49 | K53: =I53+E53
B54: в том числе:
B55: привнесенные затраты | C55: 0 | E55: 0 | G55: 0 | H55: - | I55: 0 | K55: =I55+E55
B56: собственные затраты | C56: =C53 | E56: =E53 | G56: =G53 | H56: - | I56: =I53 | K56: =I56+E56
A57: 1800 | B57: Прибыль | C57: =ROUND(C56*0.1975,2) | E57: ='20 (20д) приб (26г.)'!G43 | G57: =ROUND(G56*0.1975,2) | H57: - | I57: ='20 (20д) приб (27г.)'!G43 | K57: =E57+I57
A58: 1900 | B58: Цена продукции (без НДС) | C58: =C56+C57 | E58: =E56+E57 | G58: =G56+G57 | H58: - | I58: =I56+I57 | K58: =K56+K57
B59: Трудоемкость (чел./мес.) | C59: ='9 (9д) ОЗП НИР(ОКР)'!F23 | E59: ='9 (9д) ОЗП НИР(ОКР)'!F13 | G59: ='9 (9д) ОЗП НИР(ОКР)'!F18 | H59: - | I59: ='9 (9д) ОЗП НИР(ОКР)'!F18 | K59: =I59+E59
B63: Начальник ОФЭиАУ НИОКР | I63: Руководитель договора
B64: _____________________ Н.О. Васецкая | I64: _____________________ А.И. Боровков
B65: (подпись) (Ф.И.О.) | I65: (подпись) (Ф.И.О.)
B66: «____» __________________ 2026 г. | I66: «____» __________________ 2026 г.
I69: Ответственный исполнитель
I70: _____________________ И.О. Фамилия
I71: (подпись) (Ф.И.О.)
I72: «____» __________________ 2026 г.

Sheet Ф.2а(2ад)
IB1: Форма № 2А (2Ад)
A3: Плановая калькуляция затрат на продукцию и отчетная калькуляция затрат на аналог
CZ4: на | DF4: 2026-2027 | DX4: гг.
G6: Наименование, шифр товара, работы (услуги), | BK6: ТЕМА
G7: № этапа | BK7: 1
G8: Код по ОКП/ОКПД2 (шифр)
G9: Код по ЕКПС (при наличии)
G10: ФНН (при наличии)
G11: Калькуляционная единица | BK11: этап
BK12: (штука, комплект, этап, единица работы (услуги), иное)
G13: Техническая документация | BK13: Техническое задание №
BK14: (ТУ, ТЗ, КД, ГОСТ, иное) орган и дата утверждения
IB15: Таблица 1
A16: № № строк | G16: Наименование статьи затрат | BK16: Данные по фактическим затратам по аналогу | FF16: Планируемые затраты на продукцию
BK17: наименование материала, работы (услуги) - аналога | CC17: наименование государственного заказчика (заказчика) аналога | CU17: №, дата договора (контракта) на изготовление аналога, № этапа | DK17: наименование поставщика (исполнителя, изготовителя) аналога | EC17: сроки поставки/ выполнения/ изготовления аналога | ET17: затраты по аналогу (руб.) | FF17: коэффициент сопостави-мости_ | FS17: итого приведенные затраты (гр. 3.6 * гр. 4) | GH17: применяемый индекс цен | GX17: предложено организацией-поставщиком (подрядчиком, исполнителем) (руб.) | HM17: принято государственным заказчиком/ заказчиком
A18: 1 | G18: 2 | BK18: 3.1 | CC18: 3.2 | CU18: 3.3 | DK18: 3.4 | EC18: 3.5 | ET18: 3.6 | FF18: 4 | FS18: 5 | GH18: 6 | GX18: 7 | HM18: 8
A19: 0100 | G19: Материальные затраты - всего:
G20: в том числе:
A21: 0101 | G21: приобретение сырья, материалов и вспомогательных материалов
A22: 0102 | G22: приобретение полуфабрикатов
A23: 0103 | G23: возвратные отходы | BK23: Х | CC23: Х | CU23: Х | DK23: Х | EC23: Х | ET23: Х | FF23: Х | FS23: Х | GH23: Х
A24: 0104 | G24: приобретение комплектующих изделий
A25: 0105 | G25: оплата работ и услуг сторонних организаций производственного характера
A26: 0106 | G26: транспортно-заготовительные затраты | BK26: Х | CC26: Х | CU26: Х | DK26: Х | EC26: Х | ET26: Х | FF26: Х | FS26: Х | GH26: Х
A27: 0107 | G27: топливо на технологические цели
A28: 0108 | G28: энергия на технологические цели
A29: 0109 | G29: тара и упаковка
A30: 0110 | G30: затраты на изделия собственного производства
A31: 0200 | G31: Затраты на оплату труда - всего: | BK31: Х | CC31: Х | CU31: Х | DK31: Х | EC31: Х | ET31: Х | FF31: Х | FS31: Х | GH31: Х
G32: в том числе:
A33: 0201 | G33: основная заработная плата
A34: 0202 | G34: дополнительная заработная плата | BK34: Х | CC34: Х | CU34: Х | DK34: Х | EC34: Х | ET34: Х | FF34: Х | FS34: Х | GH34: Х
A35: 0300 | G35: Страховые взносы на обязательное социальное страхование | BK35: Х | CC35: Х | CU35: Х | DK35: Х | EC35: Х | ET35: Х | FF35: Х | FS35: Х | GH35: Х
A36: 0400 | G36: Затраты на подготовку и освоение производства - всего:
G37: в том числе:
A38: 0401 | G38: пусковые затраты
A39: 0402 | G39: затраты на подготовку и освоение новых видов продукции
A40: 0500 | G40: Затраты на специальную технологическую оснастку
A41: 0600 | G41: Затраты на специальное оборудование для научных (экспериментальных) работ
A42: 0700 | G42: Специальные затраты
A43: 0800 | G43: Общепроизводственные затраты | BK43: Х | CC43: Х | CU43: Х | DK43: Х | EC43: Х | ET43: Х | FF43: Х | FS43: Х | GH43: Х
A44: 0900 | G44: Общехозяйственные затраты | BK44: Х | CC44: Х | CU44: Х | DK44: Х | EC44: Х | ET44: Х | FF44: Х | FS44: Х | GH44: Х
A45: 1000 | G45: Затраты на командировки
A46: 1100 | G46: Прочие прямые затраты
A47: 1200 | G47: Затраты по работам (услугам), выполняемым (оказываемым) сторонними организациями
A48: 1300 | G48: Производственная себестоимость
A49: 1400 | G49: Коммерческие (внепроизводственные) затраты | BK49: Х | CC49: Х | CU49: Х | DK49: Х | EC49: Х | ET49: Х | FF49: Х | FS49: Х | GH49: Х
A50: 1500 | G50: Проценты по кредитам
A51: 1600 | G51: Административно-управленческие расходы
A52: 1700 | G52: Себестоимость продукции
G53: в том числе:
G54: привнесенные затраты
G55: собственные затраты
A56: 1800 | G56: Прибыль | BK56: Х | CC56: Х | CU56: Х | DK56: Х | EC56: Х | ET56: Х | FF56: Х | FS56: Х | GH56: Х
A57: 1900 | G57: Цена продукции (без НДС)
G58: Трудоемкость (чел./мес.) | BK58: 1. Расчетная проверка работы ТНСУ в нормальных условиях эксплуатации 2. Расчетная проверка работы ТНСУ в условиях действия ВВФ 3. Расчетная проверка работы ТНСУ после действия ВВФ | CC58: АО «НИИ мортеплотехники» | CU58: Договор №38/2022-ВТ от 22.03.2022г. этап №1 | DK58: ФГАОУ ВО «СПбПУ» | EC58: 3,50 мес. | ET58: 24.55 | FF58: =29.25/ET58 | FS58: =ROUND(ET58*FF58,2) | GH58: Х | GX58: =FS58
G61: Расшифровка затрат на командировки | IB61: Таблица 2
A62: № п/п | G62: в том числе: | BK62: Данные по фактическим затратам по аналогу | FF62: Планируемые затраты на продукцию
BK63: пункт назначения | CC63: наименование государственного заказчика (заказчика) аналога | CU63: №, дата договора (контракта) на выполнение аналога, № этапа | DK63: количество командируемых работников | EC63: длительность и даты командировки | ET63: затраты по аналогу (руб.) | FF63: коэффициент сопостави-мости | FS63: итого приведенные затраты (гр. 3.6 * гр. 4) | GH63: применяемый индекс цен | GX63: предложено организацией-поставщиком (подрядчиком, исполнителем) (руб.) | HM63: принято государственным заказчиком/ заказчиком
A64: 1 | G64: 2 | BK64: 3.1 | CC64: 3.2 | CU64: 3.3 | DK64: 3.4 | EC64: 3.5 | ET64: 3.6 | FF64: 4 | FS64: 5 | GH64: 6 | GX64: 7 | HM64: 8
A65: - | G65: - | BK65: - | CC65: - | CU65: - | DK65: - | EC65: - | ET65: - | FF65: - | FS65: - | GH65: - | GX65: - | HM65: -
G67: Начальник ОФЭиАУ НИОКР | CB67: Руководитель договора | FS67: Военный представитель
G68: _____________________ Н.О. Васецкая | CB68: _____________________ А.И. Боровков
G69: (подпись) (Ф.И.О.) | CB69: (подпись) (Ф.И.О.) | FS69: (должность) | GN69: (подпись) | HD69: (Ф.И.О.)
FS70: «____» __________________ 2026 г.
G71: «____» __________________ 2026 г. | CB71: «____» __________________ 2026 г. | FS71: М.П. (при наличии)

Sheet 9 (9д) ОЗП НИР(ОКР)
K1: Форма № 9 (9д) НИР (ОКР)
A3: РАСШИФРОВКА
B4: основной заработной платы на | C4: НИР «Радар-26», шифр C_GOZ-26, договор № ГОЗ-0412/26
C5: (НИР, ОКР, ее наименование, шифр или код)
A8: № п/п | B8: Наименование этапа, состав работ по этапу | C8: Срок выполнения этапа | D8: Количество привлекаемых специалистов | E8: Квалификационная группа основных работников, привлекаемых к выполнению этапа | F8: Трудоемкость и заработная плата, учтенные при расчете цены | N8: Примечание
F9: трудоемкость выполнения работ (чел./мес.) | G9: стоимость чел./мес. (руб.) | H9: основная заработная плата (гр.6*гр.7) | I9: в том числе доплаты и надбавки, предусмотренные законодательством Российской Федерации, относимые к основной заработной плате
I10: начисления стимулирующего характера5 | J10: начисления, обусловленные районным регулированием | K10: начисления за работу в условиях, отклоняющихся от нормальных | L10: специальные надбавки при выполнении работ, оказании услуг в командировках на территорию иностранных государств, необходимость которых определена требованиями государственного заказчика (заказчика)
A11: 1 | B11: 2 | C11: 3 | D11: 4 | E11: 5 | F11: 6 | G11: 7 | H11: 8 | I11: 9 | J11: 10 | K11: 11 | L11: 12 | N11: 13
A12: 1. | B12: ТЕМА | C12: Дата заключения договора - 01.03.2026 | D12: 5 | E12: Х | F12: 36 | G12: Х | H12: 3624000 | I12: - | J12: - | K12: - | L12: - | N12: -
B13: 2026 год, в т.ч. | C13: 01.03.2026 - 31.12.2026 | D13: 5 | E13: Научные и инженерно-технические работники, всего | F13: 36 | G13: 100666.67 | H13: 3624000 | I13: - | J13: - | K13: - | L13: - | N13: -
E14: в том числе: | I14: - | J14: - | K14: - | L14: - | N14: -
D15: 1 | E15: Старший научный сотрудник | F15: 8 | G15: 118000 | H15: 944000 | I15: - | J15: - | K15: - | L15: - | N15: -
D16: 1 | E16: Ведущий инженер | F16: 8 | G16: 110000 | H16: 880000 | I16: - | J16: - | K16: - | L16: - | N16: -
D17: 3 | E17: Инженер | F17: 20 | G17: 90000 | H17: 1800000 | I17: - | J17: - | K17: - | L17: - | N17: -
B18: 2027 год, в т.ч. | D18: =SUM(D20:D22) | E18: Научные и инженерно-технические работники, всего | F18: =SUM(F20:F22) | G18: ='22 (22д) свед. о норм_27'!D15 | H18: =ROUND(F18*G18,2) | I18: - | J18: - | K18: - | L18: - | N18: -
E19: в том числе: | I19: - | J19: - | K19: - | L19: - | N19: -
E20: Старший научный сотрудник | G20: =$G$18 | H20: =ROUND(F20*G20,2) | I20: - | J20: - | K20: - | L20: - | N20: -
E21: Ведущий инженер | G21: =$G$18 | H21: =ROUND(F21*G21,2) | I21: - | J21: - | K21: - | L21: - | N21: -
E22: Инженер | G22: =$G$18 | H22: =ROUND(F22*G22,2) | I22: - | J22: - | K22: - | L22: - | N22: -
A23: ИТОГО: | D23: =D12 | E23: Х | F23: =F12 | G23: =G12 | H23: =H12 | I23: - | J23: - | K23: - | L23: - | N23: -
B25: Начальник ОФЭиАУ НИОКР | G25: Руководитель договора
B26: _____________________ Н.О. Васецкая | G26: _____________________ А.И. Боровков
B27: (подпись) (Ф.И.О.) | G27: (подпись) (Ф.И.О.)
B28: «____» __________________ 2026 г. | G28: «____» __________________ 2026 г.
G30: Ответственный исполнитель
G31: _____________________ И.Б. Войнов
G32: (подпись) (Ф.И.О.)
G33: «____» __________________ 2026 г.
A35: 1 Информация заполняется по каждому этапу (подэтапу), в отношении которого формируется стоимостной показатель. В случае если технологический цикл производства продукции составляет более 1 года либо год начала производства продукции не соответствует году окончания ее производства и поставки (или завершения отдельных этапов поставки продукции, если государственным контрактом (контрактом) предусмотрены такие этапы), то организация представляет сведения по годам.
A36: 2 К основным работникам относятся основные производственные рабочие, инженерно-технические и другие категории работников, непосредственно участвующие в процессе производства продукции, согласно порядку определения состава затрат, включаемых в цену продукции, поставляемой в рамках государственного оборонного заказа, утвержденному в соответствии с постановлением Правительства Российской Федерации от 2 декабря 2017 года № 1465 "О государственном регулировании цен на продукцию, поставляемую по государственному оборонному заказу, а также о внесении изменений и признании утратившими силу некоторых актов Правительства Российской Федерации".
A37: 3 В случае проведения процедуры перевода в фиксированную цену других видов цен на продукцию организацией с учетом установленных в государственном контракте (контракте) условий уточнения и порядка перевода соответствующего вида цены на продукцию в фиксированную цену графы 6-13 заполняются для отражения затрат по состоянию на конкретную дату. Планируемые затраты до окончания поставки продукции в рамках выполнения государственного контракта (контракта) (или завершения отдельных этапов поставки продукции, если государственным контрактом (контрактом) предусмотрены такие этапы) необходимо заполнить в соответствии с графами 6-13, дополнив форму графами после граф, в которых представлены затраты по состоянию на конкретную дату, аналогичными по содержанию графам 6-13 (с последующей корректировкой нумерации граф) для указания планируемых затрат. В случае если технологический цикл производства продукции составляет более 1 года либо год начала производства продукции не соответствует году окончания ее производства и поставки (или завершения отдельных этапов поставки продукции, если государственным контрактом (контрактом) предусмотрены такие этапы), то организация представляет сведения о затратах по состоянию на конкретную дату в соответствии с графами 6-13 по годам, дополнив форму после графы 13 графами, аналогичными по содержанию графам 6-13 (с последующей корректировкой нумерации граф), на каждый год производства продукции для указания информации.
A38: 4 Указывается используемая единица измерения трудоемкости: нормо-час / человеко-час / человеко-день / человеко-месяц.
A39: 5 Указываются виды начислений стимулирующего характера, порядок и размеры которых определяются коллективным договором или локальным нормативным актом. Организацией представляется соответствующая выписка из документа, в котором определены указанные начисления.
A41: Используемые сокращения и их расшифровка:
A42: НИР (ОКР) – научно-исследовательская работа (опытно-конструкторская работа).

Sheet 20 (20д) приб (26г.)
A1: Форма № 20 (20д)
A3: Расчет и обоснование прибыли
A4: на 2026 г. по ТЕМА
A5: (наименование, шифр товара, работы, услуги)
G7: Таблица 1
A8: №№ строки | B8: Наименование статей затрат | C8: Затраты (руб.) | E8: Рентабельность (%) | G8: Величина прибыли (руб.)
C9: Собственные | D9: Привнесенные | E9: Собственные | F9: Привнесенные
A10: 1 | B10: 2 | C10: 3 | D10: 4 | E10: 5 | F10: 6 | G10: 7
A11: 0100 | B11: Материальные затраты - всего: | C11: Х | D11: - | E11: Х | F11: - | G11: -
B12: в том числе:
A13: 0101 | B13: приобретение сырья, материалов и вспомогательных материалов | C13: Х | D13: - | E13: Х | F13: - | G13: -
A14: 0102 | B14: приобретение полуфабрикатов | C14: Х | D14: - | E14: Х | F14: - | G14: -
A15: 0103 | B15: возвратные отходы | C15: - | D15: - | E15: - | F15: - | G15: -
A16: 0104 | B16: приобретение комплектующих изделий | C16: Х | D16: - | E16: Х | F16: - | G16: -
A17: 0105 | B17: оплата работ и услуг сторонних организаций производственного характера | C17: Х | D17: - | E17: Х | F17: - | G17: -
A18: 0106 | B18: транспортно-заготовительные затраты | C18: - | D18: - | E18: - | F18: - | G18: -
A19: 0107 | B19: топливо на технологические цели | C19: - | D19: - | E19: - | F19: - | G19: -
A20: 0108 | B20: энергия на технологические цели | C20: - | D20: - | E20: - | F20: - | G20: -
A21: 0109 | B21: тара и упаковка | C21: - | D21: - | E21: - | F21: - | G21: -
A22: 0110 | B22: затраты на изделия собственного производства | C22: - | D22: - | E22: - | F22: - | G22: -
A23: 0200 | B23: Затраты на оплату труда - всего: | C23: =C25+C26 | D23: Х | E23: 0 | F23: Х | G23: =G25+G26
B24: в том числе:
A25: 0201 | B25: основная заработная плата | C25: ='2д план кальк (2)'!E34 | D25: Х | E25: =E23 | F25: Х | G25: =ROUND(C25*E25/100,2)
A26: 0202 | B26: дополнительная заработная плата | C26: ='2д план кальк (2)'!E35 | D26: Х | E26: =E23 | F26: Х | G26: =ROUND(C26*E26/100,2)
A27: 0300 | B27: Страховые взносы на обязательное социальное страхование | C27: ='2д план кальк (2)'!E36 | D27: Х | E27: =E23 | F27: Х | G27: =ROUND(C27*E27/100,2)
A28: 0400 | B28: Затраты на подготовку и освоение производства - всего: | C28: - | D28: - | E28: - | F28: - | G28: -
B29: в том числе:
A30: 0401 | B30: пусковые затраты | C30: - | D30: - | E30: - | F30: - | G30: -
A31: 0402 | B31: затраты на подготовку и освоение новых видов продукции | C31: - | D31: - | E31: - | F31: - | G31: -
A32: 0500 | B32: Затраты на специальную технологическую оснастку | C32: - | D32: - | E32: - | F32: - | G32: -
A33: 0600 | B33: Затраты на специальное оборудование для научных (экспериментальных) работ | C33: - | D33: - | E33: - | F33: - | G33: -
A34: 0700 | B34: Специальные затраты | C34: - | D34: - | E34: - | F34: - | G34: -
A35: 0800 | B35: Общепроизводственные затраты | C35: - | D35: Х | E35: - | F35: Х | G35: -
A36: 0900 | B36: Общехозяйственные затраты | C36: ='2д план кальк (2)'!E45 | D36: Х | E36: =E23 | F36: Х | G36: =ROUND(C36*E36/100,2)
A37: 1000 | B37: Затраты на командировки | C37: - | D37: Х | E37: - | F37: Х | G37: -
A38: 1100 | B38: Прочие прямые затраты | C38: - | D38: - | E38: - | F38: - | G38: -
A39: 1200 | B39: Затраты по работам (услугам), выполняемым (оказываемым) сторонними организациями | C39: Х | D39: - | E39: Х | F39: - | G39: -
A40: 1400 | B40: Коммерческие (внепроизводственные) затраты | C40: - | D40: - | E40: - | F40: - | G40: -
A41: 1500 | B41: Проценты по кредитам | C41: Х | D41: Х | E41: Х | F41: Х | G41: -
A42: 1600 | B42: Административно-управленческие расходы | C42: - | D42: Х | E42: - | F42: Х | G42: -
A43: ИТОГО | C43: =C23+C27+C36 | D43: - | E43: Х | F43: Х | G43: =G23+G27+G36
G45: Таблица 2
A46: № п/п | B46: Мероприятия по распределению (направлению) прибыли | E46: Величина прибыли (руб.) | G46: Доля от общей массы прибыли (%)
A47: 1 | B47: 2 | E47: 3 | G47: 4
A48: 1. | B48: Налог на прибыль | E48: =ROUND(G43*0.25,2) | G48: 25
A49: 2. | B49: Развитие производства | E49: =ROUND(G43*0.75,2) | G49: 75
A50: ИТОГО | E50: =E49+E48 | G50: =G48+G49
B52: Начальник ОФЭиАУ НИОКР | E52: Руководитель договора
B53: _____________________ Н.О. Васецкая | E53: _____________________ А.И. Боровков
B54: (подпись) (Ф.И.О.) | E54: (подпись) (Ф.И.О.)
B55: «____» __________________ 2026 г. | E55: «____» __________________ 2026 г.
A56: Примечания:
A57: 1В случае если технологический цикл производства продукции составляет более 1 года либо год начала производства продукции не соответствует году окончания ее производства и поставки (или завершения отдельных этапов поставки продукции, если государственным контрактом (контрактом) предусмотрены такие этапы), то организация представляет сведения по годам.
A58: 2Заполняется для НИР (ОКР) (по каждому этапу (подэтапу), в отношении которых формируется стоимостной показатель).
A59: 3Таблица 1 заполняется в отношении затрат (включающие собственные и привнесенные) относящихся на себестоимость продукции.
A60: 4Таблица 2 заполняется в отношении только части прибыли, превышающей 25 процентов от собственных затрат, в случае предложения об установлении уровня рентабельности выше 25 процентов и не более 30 процентов собственных затрат предприятия.
A61: Используемые сокращения и их расшифровка:
A62: НИР (ОКР) – научно-исследовательская работа (опытно-конструкторская работа).
E65: Ответственный исполнитель
E66: _____________________ И.О. Фамилия
E67: (подпись) (Ф.И.О.)
E68: «____» __________________ 2026 г.

Sheet 20 (20д) приб (27г.)
A1: Форма № 20 (20д)
A3: Расчет и обоснование прибыли
A4: на 2027 г. по ТЕМА
A5: (наименование, шифр товара, работы, услуги)
G7: Таблица 1
A8: №№ строки | B8: Наименование статей затрат | C8: Затраты (руб.) | E8: Рентабельность (%) | G8: Величина прибыли (руб.)
C9: Собственные | D9: Привнесенные | E9: Собственные | F9: Привнесенные
A10: 1 | B10: 2 | C10: 3 | D10: 4 | E10: 5 | F10: 6 | G10: 7
A11: 0100 | B11: Материальные затраты - всего: | C11: Х | D11: - | E11: Х | F11: - | G11: -
B12: в том числе:
A13: 0101 | B13: приобретение сырья, материалов и вспомогательных материалов | C13: Х | D13: - | E13: Х | F13: - | G13: -
A14: 0102 | B14: приобретение полуфабрикатов | C14: Х | D14: - | E14: Х | F14: - | G14: -
A15: 0103 | B15: возвратные отходы | C15: - | D15: - | E15: - | F15: - | G15: -
A16: 0104 | B16: приобретение комплектующих изделий | C16: Х | D16: - | E16: Х | F16: - | G16: -
A17: 0105 | B17: оплата работ и услуг сторонних организаций производственного характера | C17: Х | D17: - | E17: Х | F17: - | G17: -
A18: 0106 | B18: транспортно-заготовительные затраты | C18: - | D18: - | E18: - | F18: - | G18: -
A19: 0107 | B19: топливо на технологические цели | C19: - | D19: - | E19: - | F19: - | G19: -
A20: 0108 | B20: энергия на технологические цели | C20: - | D20: - | E20: - | F20: - | G20: -
A21: 0109 | B21: тара и упаковка | C21: - | D21: - | E21: - | F21: - | G21: -
A22: 0110 | B22: затраты на изделия собственного производства | C22: - | D22: - | E22: - | F22: - | G22: -
A23: 0200 | B23: Затраты на оплату труда - всего: | C23: =C25+C26 | D23: Х | E23: 0 | F23: Х | G23: =G25+G26
B24: в том числе:
A25: 0201 | B25: основная заработная плата | C25: ='2д план кальк (2)'!I34 | D25: Х | E25: =E23 | F25: Х | G25: =ROUNDUP(C25*E25/100,2)
A26: 0202 | B26: дополнительная заработная плата | C26: ='2д план кальк (2)'!I35 | D26: Х | E26: =E23 | F26: Х | G26: =ROUND(C26*E26/100,2)
A27: 0300 | B27: Страховые взносы на обязательное социальное страхование | C27: ='2д план кальк (2)'!I36 | D27: Х | E27: =E23 | F27: Х | G27: =ROUND(C27*E27/100,2)
A28: 0400 | B28: Затраты на подготовку и освоение производства - всего: | C28: - | D28: - | E28: - | F28: - | G28: -
B29: в том числе:
A30: 0401 | B30: пусковые затраты | C30: - | D30: - | E30: - | F30: - | G30: -
A31: 0402 | B31: затраты на подготовку и освоение новых видов продукции | C31: - | D31: - | E31: - | F31: - | G31: -
A32: 0500 | B32: Затраты на специальную технологическую оснастку | C32: - | D32: - | E32: - | F32: - | G32: -
A33: 0600 | B33: Затраты на специальное оборудование для научных (экспериментальных) работ | C33: - | D33: - | E33: - | F33: - | G33: -
A34: 0700 | B34: Специальные затраты | C34: - | D34: - | E34: - | F34: - | G34: -
A35: 0800 | B35: Общепроизводственные затраты | C35: - | D35: Х | E35: - | F35: Х | G35: -
A36: 0900 | B36: Общехозяйственные затраты | C36: ='2д план кальк (2)'!I45 | D36: Х | E36: =E23 | F36: Х | G36: =ROUNDUP(C36*E36/100,2)
A37: 1000 | B37: Затраты на командировки | C37: - | D37: Х | E37: - | F37: Х | G37: -
A38: 1100 | B38: Прочие прямые затраты | C38: - | D38: - | E38: - | F38: - | G38: -
A39: 1200 | B39: Затраты по работам (услугам), выполняемым (оказываемым) сторонними организациями | C39: Х | D39: - | E39: Х | F39: - | G39: -
A40: 1400 | B40: Коммерческие (внепроизводственные) затраты | C40: - | D40: - | E40: - | F40: - | G40: -
A41: 1500 | B41: Проценты по кредитам | C41: Х | D41: Х | E41: Х | F41: Х | G41: -
A42: 1600 | B42: Административно-управленческие расходы | C42: - | D42: Х | E42: - | F42: Х | G42: -
A43: ИТОГО | C43: =C23+C27+C36 | D43: - | E43: Х | F43: Х | G43: =G23+G27+G36
G45: Таблица 2
A46: № п/п | B46: Мероприятия по распределению (направлению) прибыли | E46: Величина прибыли (руб.) | G46: Доля от общей массы прибыли (%)
A47: 1 | B47: 2 | E47: 3 | G47: 4
A48: 1. | B48: Налог на прибыль | E48: =ROUND(G43*0.25,2) | G48: 25
A49: 2. | B49: Развитие производства | E49: =ROUND(G43*0.75,2) | G49: 75
A50: ИТОГО | E50: =E49+E48 | G50: =G48+G49
B52: Начальник ОФЭиАУ НИОКР | E52: Руководитель договора
B53: _____________________ Н.О. Васецкая | E53: _____________________ А.И. Боровков
B54: (подпись) (Ф.И.О.) | E54: (подпись) (Ф.И.О.)
B55: «____» __________________ 2026 г. | E55: «____» __________________ 2026 г.
A56: Примечания:
A57: 1В случае если технологический цикл производства продукции составляет более 1 года либо год начала производства продукции не соответствует году окончания ее производства и поставки (или завершения отдельных этапов поставки продукции, если государственным контрактом (контрактом) предусмотрены такие этапы), то организация представляет сведения по годам.
A58: 2Заполняется для НИР (ОКР) (по каждому этапу (подэтапу), в отношении которых формируется стоимостной показатель).
A59: 3Таблица 1 заполняется в отношении затрат (включающие собственные и привнесенные) относящихся на себестоимость продукции.
A60: 4Таблица 2 заполняется в отношении только части прибыли, превышающей 25 процентов от собственных затрат, в случае предложения об установлении уровня рентабельности выше 25 процентов и не более 30 процентов собственных затрат предприятия.
A61: Используемые сокращения и их расшифровка:
A62: НИР (ОКР) – научно-исследовательская работа (опытно-конструкторская работа).
E65: Ответственный исполнитель
E66: _____________________ И.О. Фамилия
E67: (подпись) (Ф.И.О.)
E68: «____» __________________ 2026 г.

Sheet 22 (22д) свед. о норм_25
D1: Форма № 22 (22д)
D3: УТВЕРЖДАЮ
D5: Проректор по научной работе ФГАОУ ВО «СПбПУ»
D6: __________________________ Ю.В. Фомин
D7: (подпись) (Ф.И.О.)
D8: «____» __________________ 2025 г.
A10: Сведения о нормативах и экономических показателях ФГАОУ ВО «СПбПУ», используемых при определении стоимости работ по договорам в рамках ГОЗ на 2025 год
A12: № п/п | B12: Наименование | C12: Единица измерения | D12: Значение | E12: Основание
A13: 1 | B13: 2 | C13: 3 | D13: 4 | E13: 5
A14: 1. | B14: Сведения по затратам на оплату труда:
A15: 1.1 | B15: среднемесячная заработная плата основных работников | C15: руб. | D15: 0 | E15: Письмо 550 ВП МО РФ № 115/550/238 от 05.05.2025г.
A16: 1.2 | B16: дополнительная заработная плата основных работников | C16: % | D16: 0 | E16: форма 10 (10д)
A17: 1.3 | B17: дополнительная заработная плата инженерно-технических и научных работников | C17: % | D17: 0 | E17: Приказ по ФГАОУ ВО "СПбПУ" о формировании отпускного фонда с 2018г.
A18: 1.4 | B18: дополнительная заработная плата профессорско-преподавательского состава | C18: % | D18: 0 | E18: Приказ по ФГАОУ ВО "СПбПУ" о формировании отпускного фонда с 2018г.
A19: 2. | B19: Отчисления от фонда оплаты труда: | C19: % | D19: =D20+D21
A20: 2.1 | B20: страховые взносы | C20: % | D20: 30
A21: 2.2 | B21: страховые взносы на обязательное страхование от несчастных случаев на производстве и профессиональных заболеваний | C21: % | D21: 0.2 | E21: уведомление ФСС
A22: 3. | B22: Общехозяйственные затраты (административно-управленческие расходы) / база распределения затрат (основная заработная плата) | C22: % | D22: 32 | E22: Письмо 550 ВП МО РФ № 115/550/238 от 05.05.2025г.
A23: 4. | B23: Общепроизводственные затраты / база распределения затрат (______________________________) | C23: % | D23: - | E23: -
A24: 5. | B24: Коммерческие (внепроизводственные) затраты / база распределения затрат (_________________________________________) | C24: % | D24: - | E24: -
A25: 6. | B25: Транспортно-заготовительные затраты / база распределения затрат (_________________________________________) | C25: % | D25: - | E25: -
A27: Начальник ОФЭАУ НИОКР ФГАОУ ВО «СПбПУ» | C27: _________________________ Н.О. Васецкая
C28: (подпись) (Ф.И.О.)
C29: «____» __________________ 2026 г.
A30: 1 В случае если этапы НИР (ОКР) выполняются в одном году, то формы, содержащие информацию о финансово-хозяйственной деятельности организации в целом (формы №№ 8 (8д), 10 (10д), 11 (11д), 12 (12д), 13 (13д), 21, 21д, 22 (22д), 23, 23д приложения № 5 к настоящему приказу), представляются единожды в составе соответствующего предложения о цене. При наличии различных уровней нормативов и экономических показателей для различных подразделений организации-потенциального поставщика (подрядчика, исполнителя) представляются сведения по каждому такому подразделению.
A31: 2 При проведении процедуры перевода в фиксированную цену других видов цен на продукцию организацией указываются значения, используемые при определении фиксированной цены в соответствии с установленными в государственном контракте (контракте) условиями уточнения и порядка перевода соответствующего вида цены на продукцию в фиксированную цену. В случае если технологический цикл производства продукции составляет более 1 года либо год начала производства продукции не соответствует году окончания ее производства и поставки (или завершения отдельных этапов поставки продукции, если государственным контрактом (контрактом) предусмотрены такие этапы), то организация представляет сведения с разбивкой по годам для указания информации.
A32: 3 С указанием наименования и реквизитов подтверждающих (обосновывающих) документов (при наличии).
A33: 4 Указывается используемая единица измерения трудоемкости: нормо-час / человеко-час / человеко-день / человеко-месяц.
A34: 5 К основным работникам относятся основные производственные рабочие, инженерно-технические и другие категории работников, непосредственно участвующие в процессе производства продукции, согласно порядку определения состава затрат, включаемых в цену продукции, поставляемой в рамках государственного оборонного заказа, утвержденному в соответствии с постановлением Правительства Российской Федерации от 2 декабря 2017 года № 1465 "О государственном регулировании цен на продукцию, поставляемую по государственному оборонному заказу, а также о внесении изменений и признании утратившими силу некоторых актов Правительства Российской Федерации".
A35: 6 Указывается метод распределения затрат в соответствии с принятой на предприятии учетной политикой на соответствующий год.
A37: Используемые сокращения и их расшифровка:
B38: ИТР – инженерно-технический работник; НИР (ОКР) – научно-исследовательская работа (опытно-конструкторская работа).

Sheet 22 (22д) свед. о норм_26
D1: Форма № 22 (22д)
E3: УТВЕРЖДАЮ
E5: Проректор по научной работе ФГАОУ ВО «СПбПУ»
E6: __________________________ Ю.В. Фомин
E7: (подпись) (Ф.И.О.)
E8: «____» __________________ 2026 г.
A10: Сведения о нормативах и экономических показателях ФГАОУ ВО «СПбПУ», используемых при определении стоимости работ по договорам в рамках ГОЗ на 2026 год
A12: № п/п | B12: Наименование | C12: Единица измерения | D12: Значение | E12: Основание
A13: 1 | B13: 2 | C13: 3 | D13: 4 | E13: 5
A14: 1. | B14: Сведения по затратам на оплату труда:
A15: 1.1 | B15: среднемесячная заработная плата основных работников | C15: руб. | D15: 112261 | E15: Письмо 550 ВП МО РФ № 115/550/231/1 от 25.05.2026г.
A16: 1.2 | B16: дополнительная заработная плата основных работников | C16: % | D16: 8.6866 | E16: форма 10 (10д)
A17: 1.3 | B17: дополнительная заработная плата инженерно-технических и научных работников | C17: % | D17: 0 | E17: Приказ по ФГАОУ ВО "СПбПУ" о формировании отпускного фонда с 2018г.
A18: 1.4 | B18: дополнительная заработная плата профессорско-преподавательского состава | C18: % | D18: 0 | E18: Приказ по ФГАОУ ВО "СПбПУ" о формировании отпускного фонда с 2018г.
A19: 2. | B19: Отчисления от фонда оплаты труда: | C19: % | D19: =D20+D21
A20: 2.1 | B20: страховые взносы | C20: % | D20: 30
A21: 2.2 | B21: страховые взносы на обязательное страхование от несчастных случаев на производстве и профессиональных заболеваний | C21: % | D21: 0.2 | E21: уведомление ФСС
A22: 3. | B22: Общехозяйственные затраты (административно-управленческие расходы) / база распределения затрат (основная заработная плата) | C22: % | D22: 0 | E22: Письмо 550 ВП МО РФ № 115/550/231/1 от 25.05.2026г.
A23: 4. | B23: Общепроизводственные затраты / база распределения затрат (______________________________) | C23: % | D23: - | E23: -
A24: 5. | B24: Коммерческие (внепроизводственные) затраты / база распределения затрат (_________________________________________) | C24: % | D24: - | E24: -
A25: 6. | B25: Транспортно-заготовительные затраты / база распределения затрат (_________________________________________) | C25: % | D25: - | E25: -
A27: Начальник ОФЭАУ НИОКР ФГАОУ ВО «СПбПУ» | C27: _________________________ Н.О. Васецкая
C28: (подпись) (Ф.И.О.)
C29: «____» __________________ 2026 г.
A30: 1 В случае если этапы НИР (ОКР) выполняются в одном году, то формы, содержащие информацию о финансово-хозяйственной деятельности организации в целом (формы №№ 8 (8д), 10 (10д), 11 (11д), 12 (12д), 13 (13д), 21, 21д, 22 (22д), 23, 23д приложения № 5 к настоящему приказу), представляются единожды в составе соответствующего предложения о цене. При наличии различных уровней нормативов и экономических показателей для различных подразделений организации-потенциального поставщика (подрядчика, исполнителя) представляются сведения по каждому такому подразделению.
A31: 2 При проведении процедуры перевода в фиксированную цену других видов цен на продукцию организацией указываются значения, используемые при определении фиксированной цены в соответствии с установленными в государственном контракте (контракте) условиями уточнения и порядка перевода соответствующего вида цены на продукцию в фиксированную цену. В случае если технологический цикл производства продукции составляет более 1 года либо год начала производства продукции не соответствует году окончания ее производства и поставки (или завершения отдельных этапов поставки продукции, если государственным контрактом (контрактом) предусмотрены такие этапы), то организация представляет сведения с разбивкой по годам для указания информации.
A32: 3 С указанием наименования и реквизитов подтверждающих (обосновывающих) документов (при наличии).
A33: 4 Указывается используемая единица измерения трудоемкости: нормо-час / человеко-час / человеко-день / человеко-месяц.
A34: 5 К основным работникам относятся основные производственные рабочие, инженерно-технические и другие категории работников, непосредственно участвующие в процессе производства продукции, согласно порядку определения состава затрат, включаемых в цену продукции, поставляемой в рамках государственного оборонного заказа, утвержденному в соответствии с постановлением Правительства Российской Федерации от 2 декабря 2017 года № 1465 "О государственном регулировании цен на продукцию, поставляемую по государственному оборонному заказу, а также о внесении изменений и признании утратившими силу некоторых актов Правительства Российской Федерации".
A35: 6 Указывается метод распределения затрат в соответствии с принятой на предприятии учетной политикой на соответствующий год.
A37: Используемые сокращения и их расшифровка:
B38: ИТР – инженерно-технический работник; НИР (ОКР) – научно-исследовательская работа (опытно-конструкторская работа).

Sheet 22 (22д) свед. о норм_27
D1: Форма № 22 (22д)
D3: УТВЕРЖДАЮ
D5: Проректор по научной работе ФГАОУ ВО «СПбПУ»
D6: __________________________ Ю.В. Фомин
D7: (подпись) (Ф.И.О.)
D8: «____» __________________ 2026 г.
A10: Сведения о нормативах и экономических показателях ФГАОУ ВО «СПбПУ», используемых при определении стоимости работ по договорам в рамках ГОЗ на 2027 год
A12: № п/п | B12: Наименование | C12: Единица измерения | D12: Значение | E12: Основание
A13: 1 | B13: 2 | C13: 3 | D13: 4 | E13: 5
A14: 1. | B14: Сведения по затратам на оплату труда:
A15: 1.1 | B15: среднемесячная заработная плата основных работников | C15: руб. | D15: =ROUND('22 (22д) свед. о норм_26'!D15*1.04*1.039,0) | E15: Норматив 2026 с учетом письма Мин.эконом.развития №37099-ПК/Д03и от 30.09.2025 применены индексы: 2027 ИПЦ-1,04 и ИРЗП-1,039
A16: 1.2 | B16: дополнительная заработная плата основных работников | C16: % | D16: 0 | E16: форма 10 (10д)
A17: 1.3 | B17: дополнительная заработная плата инженерно-технических и научных работников | C17: % | D17: 0 | E17: Приказ по ФГАОУ ВО "СПбПУ" о формировании отпускного фонда с 2018г.
A18: 1.4 | B18: дополнительная заработная плата профессорско-преподавательского состава | C18: % | D18: 0 | E18: Приказ по ФГАОУ ВО "СПбПУ" о формировании отпускного фонда с 2018г.
A19: 2. | B19: Отчисления от фонда оплаты труда: | C19: % | D19: =D20+D21
A20: 2.1 | B20: страховые взносы | C20: % | D20: 30
A21: 2.2 | B21: страховые взносы на обязательное страхование от несчастных случаев на производстве и профессиональных заболеваний | C21: % | D21: 0.2 | E21: уведомление ФСС
A22: 3. | B22: Общехозяйственные затраты (административно-управленческие расходы) / база распределения затрат (основная заработная плата) | C22: % | D22: 32 | E22: форма 12
A23: 4. | B23: Общепроизводственные затраты / база распределения затрат (______________________________) | C23: % | D23: - | E23: -
A24: 5. | B24: Коммерческие (внепроизводственные) затраты / база распределения затрат (_________________________________________) | C24: % | D24: - | E24: -
A25: 6. | B25: Транспортно-заготовительные затраты / база распределения затрат (_________________________________________) | C25: % | D25: - | E25: -
A27: Начальник ОФЭАУ НИОКР ФГАОУ ВО «СПбПУ» | C27: _________________________ Н.О. Васецкая
C28: (подпись) (Ф.И.О.)
C29: «____» __________________ 2026 г.
A31: 1 В случае если этапы НИР (ОКР) выполняются в одном году, то формы, содержащие информацию о финансово-хозяйственной деятельности организации в целом (формы №№ 8 (8д), 10 (10д), 11 (11д), 12 (12д), 13 (13д), 21, 21д, 22 (22д), 23, 23д приложения № 5 к настоящему приказу), представляются единожды в составе соответствующего предложения о цене. При наличии различных уровней нормативов и экономических показателей для различных подразделений организации-потенциального поставщика (подрядчика, исполнителя) представляются сведения по каждому такому подразделению.
A32: 2 При проведении процедуры перевода в фиксированную цену других видов цен на продукцию организацией указываются значения, используемые при определении фиксированной цены в соответствии с установленными в государственном контракте (контракте) условиями уточнения и порядка перевода соответствующего вида цены на продукцию в фиксированную цену. В случае если технологический цикл производства продукции составляет более 1 года либо год начала производства продукции не соответствует году окончания ее производства и поставки (или завершения отдельных этапов поставки продукции, если государственным контрактом (контрактом) предусмотрены такие этапы), то организация представляет сведения с разбивкой по годам для указания информации.
A33: 3 С указанием наименования и реквизитов подтверждающих (обосновывающих) документов (при наличии).
A34: 4 Указывается используемая единица измерения трудоемкости: нормо-час / человеко-час / человеко-день / человеко-месяц.
A35: 5 К основным работникам относятся основные производственные рабочие, инженерно-технические и другие категории работников, непосредственно участвующие в процессе производства продукции, согласно порядку определения состава затрат, включаемых в цену продукции, поставляемой в рамках государственного оборонного заказа, утвержденному в соответствии с постановлением Правительства Российской Федерации от 2 декабря 2017 года № 1465 "О государственном регулировании цен на продукцию, поставляемую по государственному оборонному заказу, а также о внесении изменений и признании утратившими силу некоторых актов Правительства Российской Федерации".
A36: 6 Указывается метод распределения затрат в соответствии с принятой на предприятии учетной политикой на соответствующий год.
A38: Используемые сокращения и их расшифровка:
B39: ИТР – инженерно-технический работник; НИР (ОКР) – научно-исследовательская работа (опытно-конструкторская работа).

Sheet 10 (10д) ДЗП (КФО2) (25-27)
H1: Форма № 10 (10д)
B3: Расчет-обоснование уровня (%) дополнительной заработной платы основных работников попо приносящей доход деятельности (КФО 2) на 2025-2027 гг
B4: по ФГАОУ ВО «Санкт-Петербургский политехнический университет Петра Великого»
B5: (наименование организации-поставщика (подрядчика, исполнителя))
H6: (руб.)
A7: № п/п | B7: Наименование | C7: Период, предшествующий отчетному (2023 г.) | D7: Отчетный период / период, предшествующий планируемому (2024 г.) | F7: Планируемый период (2025 г.) | G7: Планируемый период (2026 г.) | H7: Планируемый период (2027 г.)
C8: факт | D8: план | E8: факт | F8: план | G8: план | H8: план
A9: 1 | B9: 2 | C9: 3 | D9: 4.1 | E9: 4.2 | F9: 5 | G9: 6 | H9: 7
A10: 1. | B10: Основная заработная плата основных работников | C10: 0 | D10: 0 | E10: 0 | F10: 0 | G10: 0 | H10: 0
A11: 2. | B11: Дополнительная заработная плата основных работников, | C11: 0 | D11: 0 | E11: 0 | F11: 0 | G11: 0 | H11: 0
A12: 2.1 | B12: в % к основной заработной плате основных работников, % | C12: =C11/C10 | D12: =D11/D10 | E12: =E11/E10 | F12: =F11/F10 | G12: =G11/G10 | H12: =H11/H10
A14: Структура дополнительной заработной платы
H15: (руб.)
A16: № п/п | B16: Наименование выплат | C16: Период, предшествующий отчетному (2023 г.) | D16: Отчетный период / период, предшествующий планируемому (2024 г.) | F16: Планируемый период (2025 г.) | G16: Планируемый период (2026 г.) | H16: Планируемый период (2027 г.)
C17: факт | D17: план | E17: факт | F17: план | G17: план | H17: план
A18: 1 | B18: 2 | C18: 3 | D18: 4.1 | E18: 4.2 | F18: 5 | G18: 6 | H18: 7
A19: 1. | B19: Выплаты отпусков работникам из резервного отпускного фонда | C19: =C11 | D19: =D11 | E19: =E11 | F19: =F11 | G19: =G11 | H19: =H11
A20: ИТОГО | C20: =C19 | D20: =D19 | E20: =E19 | F20: =F19 | G20: =G19 | H20: =H19
B22: Начальник ОФЭАУ НИОКР | F22: Главный бухгалтер ФГАОУ ВО «СПБПУ»
B23: __________________________ Н.О. Васецкая | F23: ________________________ Н.В. Иванова
B24: (подпись) (Ф.И.О.) | F24: (подпись) (Ф.И.О.)
B25: «____» __________________ 2026 г. | F25: «____» __________________ 2026 г.
A27: 1 При наличии различных уровней дополнительной заработной платы основных работников для различных подразделений организации-потенциального поставщика (подрядчика, исполнителя) представляются расчеты-обоснования по каждому такому подразделению.
A28: 2 К основным работникам относятся основные производственные рабочие, инженерно-технические и другие категории работников, непосредственно участвующие в процессе производства продукции, согласно порядку определения состава затрат, включаемых в цену продукции, поставляемой в рамках государственного оборонного заказа, утвержденному в соответствии с постановлением Правительства Российской Федерации от 2 декабря 2017 года № 1465 "О государственном регулировании цен на продукцию, поставляемую по государственному оборонному заказу, а также о внесении изменений и признании утратившими силу некоторых актов Правительства Российской Федерации".
A29: 3 В случае если технологический цикл производства продукции составляет более 1 года либо год начала производства продукции не соответствует году окончания ее производства и поставки (или завершения отдельных этапов поставки продукции, если государственным контрактом (контрактом) предусмотрены такие этапы), то организация представляет сведения по годам.
A30: 4 В случае если этапы НИР (ОКР) выполняются в одном году, то формы, содержащие информацию о финансово-хозяйственной деятельности организации в целом (формы №№ 8 (8д), 10 (10д), 11 (11д), 12 (12д), 13 (13д), 21, 21д, 22 (22д), 23, 23д приложения № 5 к настоящему приказу), представляются единожды в составе соответствующего предложения о цене.
A31: 5 При проведении процедуры перевода в фиксированную цену других видов цен на продукцию организацией с учетом установленных в государственном контракте (контракте) условий уточнения и порядка перевода соответствующего вида цены на продукцию в фиксированную цену в графе 5 представляются планируемые затраты года окончания поставки продукции в рамках выполнения государственного контракта (контракта) (или завершения отдельных этапов поставки продукции, если государственным контрактом (контрактом) предусмотрены такие этапы). В случае если технологический цикл производства продукции составляет более 1 года либо год начала производства продукции не соответствует году окончания ее производства и поставки (или завершения отдельных этапов поставки продукции, если государственным контрактом (контрактом) предусмотрены такие этапы), то организация представляет сведения о затратах по годам, предшествующим году поставки продукции, в соответствии с графами 4.1-4.2 на каждый год производства продукции, дополнив форму после графы 4.2 графами, аналогичными по содержанию графам 4.1-4.2 соответственно (с последующей корректировкой нумерации граф), для указания информации.
A32: 6 Указываются выплаты, предусмотренные локальным нормативным актом организации или нормативным правовым актом Российской Федерации, а также представляется такой локальный нормативный акт или оформляется ссылка на конкретную структурную единицу нормативных правовых актов Российской Федерации, являющихся основанием указанных выплат за счет фонда дополнительной заработной платы из состава себестоимости организации; при удельном весе более 10 процентов представляется расшифровка выплат.
A34: Используемые сокращения и их расшифровка:
B35: ГОЗ – государственный оборонный заказ; НИР (ОКР) – научно-исследовательская работа (опытно-конструкторская работа).

Sheet 10 (10д) ДЗП (ГОЗ) (25-27)
H1: Форма № 10 (10д)
B3: Расчет-обоснование уровня (%) дополнительной заработной платы основных работников по договорам в рамках ГОЗ на 2025-2027 гг
B4: по ФГАОУ ВО «Санкт-Петербургский политехнический университет Петра Великого»
B5: (наименование организации-поставщика (подрядчика, исполнителя))
H6: (руб.)
A7: № п/п | B7: Наименование | C7: Период, предшествующий отчетному (2023 г.) | D7: Отчетный период / период, предшествующий планируемому (2024 г.) | F7: Планируемый период (2025 г.) | G7: Планируемый период (2026 г.) | H7: Планируемый период (2027 г.)
C8: факт | D8: план | E8: факт | F8: план | G8: план | H8: план
A9: 1 | B9: 2 | C9: 3 | D9: 4.1 | E9: 4.2 | F9: 5 | G9: 6 | H9: 7
A10: 1. | B10: Основная заработная плата основных работников | C10: 0 | D10: 0 | E10: 0 | F10: 0 | G10: 0 | H10: 0
A11: 2. | B11: Дополнительная заработная плата основных работников, | C11: 0 | D11: 0 | E11: 0 | F11: 0 | G11: 0 | H11: 0
A12: 2.1 | B12: в % к основной заработной плате основных работников, % | C12: =C11/C10 | D12: =D11/D10 | E12: =E11/E10 | F12: =F11/F10 | G12: =G11/G10 | H12: =H11/H10
A14: Структура дополнительной заработной платы
H15: (руб.)
A16: № п/п | B16: Наименование выплат | C16: Период, предшествующий отчетному (2023 г.) | D16: Отчетный период / период, предшествующий планируемому (2024 г.) | F16: Планируемый период (2025 г.) | G16: Планируемый период (2026 г.) | H16: Планируемый период (2027 г.)
C17: факт | D17: план | E17: факт | F17: план | G17: план | H17: план
A18: 1 | B18: 2 | C18: 3 | D18: 4.1 | E18: 4.2 | F18: 5 | G18: 6 | H18: 7
A19: 1. | B19: Выплаты отпусков работникам из резервного отпускного фонда | C19: =C11 | D19: =D11 | E19: =E11 | F19: =F11 | G19: =G11 | H19: =H11
A20: ИТОГО | C20: =C19 | D20: =D19 | E20: =E19 | F20: =F19 | G20: =G19 | H20: =H19
B22: Начальник ОФЭАУ НИОКР | F22: Главный бухгалтер ФГАОУ ВО «СПБПУ»
B23: __________________________ Н.О. Васецкая | F23: ________________________ Н.В. Иванова
B24: (подпись) (Ф.И.О.) | F24: (подпись) (Ф.И.О.)
B25: «____» __________________ 2026 г. | F25: «____» __________________ 2026 г.
A27: 1 При наличии различных уровней дополнительной заработной платы основных работников для различных подразделений организации-потенциального поставщика (подрядчика, исполнителя) представляются расчеты-обоснования по каждому такому подразделению.
A28: 2 К основным работникам относятся основные производственные рабочие, инженерно-технические и другие категории работников, непосредственно участвующие в процессе производства продукции, согласно порядку определения состава затрат, включаемых в цену продукции, поставляемой в рамках государственного оборонного заказа, утвержденному в соответствии с постановлением Правительства Российской Федерации от 2 декабря 2017 года № 1465 "О государственном регулировании цен на продукцию, поставляемую по государственному оборонному заказу, а также о внесении изменений и признании утратившими силу некоторых актов Правительства Российской Федерации".
A29: 3 В случае если технологический цикл производства продукции составляет более 1 года либо год начала производства продукции не соответствует году окончания ее производства и поставки (или завершения отдельных этапов поставки продукции, если государственным контрактом (контрактом) предусмотрены такие этапы), то организация представляет сведения по годам.
A30: 4 В случае если этапы НИР (ОКР) выполняются в одном году, то формы, содержащие информацию о финансово-хозяйственной деятельности организации в целом (формы №№ 8 (8д), 10 (10д), 11 (11д), 12 (12д), 13 (13д), 21, 21д, 22 (22д), 23, 23д приложения № 5 к настоящему приказу), представляются единожды в составе соответствующего предложения о цене.
A31: 5 При проведении процедуры перевода в фиксированную цену других видов цен на продукцию организацией с учетом установленных в государственном контракте (контракте) условий уточнения и порядка перевода соответствующего вида цены на продукцию в фиксированную цену в графе 5 представляются планируемые затраты года окончания поставки продукции в рамках выполнения государственного контракта (контракта) (или завершения отдельных этапов поставки продукции, если государственным контрактом (контрактом) предусмотрены такие этапы). В случае если технологический цикл производства продукции составляет более 1 года либо год начала производства продукции не соответствует году окончания ее производства и поставки (или завершения отдельных этапов поставки продукции, если государственным контрактом (контрактом) предусмотрены такие этапы), то организация представляет сведения о затратах по годам, предшествующим году поставки продукции, в соответствии с графами 4.1-4.2 на каждый год производства продукции, дополнив форму после графы 4.2 графами, аналогичными по содержанию графам 4.1-4.2 соответственно (с последующей корректировкой нумерации граф), для указания информации.
A32: 6 Указываются выплаты, предусмотренные локальным нормативным актом организации или нормативным правовым актом Российской Федерации, а также представляется такой локальный нормативный акт или оформляется ссылка на конкретную структурную единицу нормативных правовых актов Российской Федерации, являющихся основанием указанных выплат за счет фонда дополнительной заработной платы из состава себестоимости организации; при удельном весе более 10 процентов представляется расшифровка выплат.
A34: Используемые сокращения и их расшифровка:
B35: ГОЗ – государственный оборонный заказ; НИР (ОКР) – научно-исследовательская работа (опытно-конструкторская работа).

Sheet 12 ОХР (КФО2_ГОЗ) (25-27)
O1: Форма № 12
B3: Смета и расчет
B4: общехозяйственных затрат по приносящей доход деятельности (КФО 2) на 2025-2027 гг по ФГАОУ ВО «Санкт-Петербургский политехнический университет Петра Великого»
B5: (наименование организации-поставщика (подрядчика, исполнителя))
O6: (руб.)
A7: № п/п | B7: Наименование статей | C7: Отчетный период / период, предшествующий планируемому (год 2024) | G7: применяемый индекс цен | H7: Планируемый период (год 2025) | J7: применяемый индекс цен | K7: Планируемый период (год 2026) | M7: применяемый индекс цен5 | N7: Планируемый период (год 2027)
C8: план | E8: факт | H8: предложено организацией-поставщиком (подрядчиком, исполнителем) | K8: предложено организацией-поставщиком (подрядчиком, исполнителем) | N8: предложено организацией-поставщиком (подрядчиком, исполнителем)
C9: всего | D9: в том числе по госконтрактам (контрактам) ГОЗ | E9: всего | F9: в том числе по госконтрактам (контрактам) ГОЗ | H9: всего | I9: в том числе по госконтрактам (контрактам) ГОЗ | K9: всего | L9: в том числе по госконтрактам (контрактам) ГОЗ | N9: всего | O9: в том числе по госконтрактам (контрактам) ГОЗ
A10: 1 | B10: 2 | C10: 3 | D10: 4 | E10: 5 | F10: 6 | G10: 7 | H10: 8 | I10: 9 | J10: 10 | K10: 11 | L10: 12 | M10: 13 | N10: 14 | O10: 15
A11: 1 | B11: 211 Заработная плата | C11: 0 | D11: 0 | E11: 0 | F11: 0 | H11: 0 | I11: 0 | K11: 0 | L11: 0 | N11: 0 | O11: 0
A12: 2 | B12: 212 Прочие выплаты | C12: 0 | D12: 0 | E12: 0 | F12: 0 | H12: 0 | I12: 0 | K12: 0 | L12: 0 | N12: 0 | O12: 0
A13: 3 | B13: 213 Начисления на оплату труда | C13: 0 | D13: 0 | E13: 0 | F13: 0 | H13: 0 | I13: 0 | K13: 0 | L13: 0 | N13: 0 | O13: 0
A14: 4 | B14: 221 Услуги связи | C14: 0 | D14: 0 | E14: 0 | F14: 0 | H14: 0 | I14: 0 | K14: 0 | L14: 0 | N14: 0 | O14: 0
A15: 5 | B15: 222 Транспортные услуги | C15: 0 | D15: 0 | E15: 0 | F15: 0 | H15: 0 | I15: 0 | K15: 0 | L15: 0 | N15: 0 | O15: 0
A16: 6 | B16: 223 Коммунальные услуги | C16: 0 | D16: 0 | E16: 0 | F16: 0 | H16: 0 | I16: 0 | K16: 0 | L16: 0 | N16: 0 | O16: 0
A17: 7 | B17: 224 Арендная плата за пользование имуществом | C17: 0 | D17: 0 | E17: 0 | F17: 0 | H17: 0 | I17: 0 | K17: 0 | L17: 0 | N17: 0 | O17: 0
A18: 8 | B18: 225 Услуги по содержанию имущества | C18: 0 | D18: 0 | E18: 0 | F18: 0 | H18: 0 | I18: 0 | K18: 0 | L18: 0 | N18: 0 | O18: 0
A19: 9 | B19: 226 Прочие услуги | C19: 0 | D19: 0 | E19: 0 | F19: 0 | H19: 0 | I19: 0 | K19: 0 | L19: 0 | N19: 0 | O19: 0
A20: 10 | B20: 226 Расходы на амортизацию прав пользования НМА | C20: 0 | D20: 0 | E20: 0 | F20: 0 | H20: 0 | I20: 0 | K20: 0 | L20: 0 | N20: 0 | O20: 0
A21: 11 | B21: 227 Страхование | C21: 0 | D21: 0 | E21: 0 | F21: 0 | H21: 0 | I21: 0 | K21: 0 | L21: 0 | N21: 0 | O21: 0
A22: 13 | B22: 266 Социальные пособия и компенсации персоналу в денежной форме | C22: 0 | D22: 0 | E22: 0 | F22: 0 | H22: 0 | I22: 0 | K22: 0 | L22: 0 | N22: 0 | O22: 0
... A26: 17 | B26: 297 Иные выплаты текущего характера организациям | C26: 0 | D26: 0 | E26: 0 | F26: 0 | H26: 0 | I26: 0 | K26: 0 | L26: 0 | N26: 0 | O26: 0
A27: ИТОГО | C27: =SUM(C11:C26) | D27: =SUM(D11:D26) | E27: =SUM(E11:E26) | F27: =SUM(F11:F26) | H27: =SUM(H11:H26) | I27: =SUM(I11:I26) | K27: =SUM(K11:K26) | L27: =SUM(L11:L26) | N27: =SUM(N11:N26) | O27: =SUM(O11:O26)
A28: База распределения общехозяйственных затрат / административно-управленческих расходов (основная заработная плата)6 | C28: 0 | D28: 0 | E28: 0 | F28: 0 | H28: 0 | I28: 0 | K28: 0 | L28: 0 | N28: 0 | O28: 0
A29: Отношение общехозяйственных затрат / административно-управленческих расходов к базе распределения, % | C29: =C27/C28 | D29: =D27/D28 | E29: =E27/E28 | F29: =F27/F28 | H29: =H27/H28 | I29: =I27/I28 | K29: =K27/K28 | L29: =L27/L28 | N29: =N27/N28 | O29: =O27/O28
B31: Начальник ОФЭАУ НИОКР | I31: Главный бухгалтер ФГАОУ ВО «СПБПУ»
B32: __________________________ Н.О. Васецкая | I32: __________________________ Н.В. Иванова
B33: (подпись) (Ф.И.О.) | I33: (подпись) (Ф.И.О.)
B34: «____» __________________ 2026 г. | I34: «____» __________________ 2026 г.
A36: 1 Административно-управленческие расходы применяются в случае если учётной политикой организации расходы, связанные с управлением деятельностью организации в целом, признаются расходами отчетного периода, в котором они возникли, и предусмотрено отнесение указанных затрат на финансовый результат государственного контракта (контракта) (согласно порядку определения состава затрат, включаемых в цену продукции, поставляемой в рамках государственного оборонного заказа, утвержденному в соответствии с постановлением Правительства Российской Федерации от 2 декабря 2017 года № 1465 "О государственном регулировании цен на продукцию, поставляемую по государственному оборонному заказу, а также о внесении изменений и признании утратившими силу некоторых актов Правительства Российской Федерации" (далее - Порядок)). При наличии различных уровней общехозяйственных затрат / административно-управленческих расходов для различных подразделений организации-потенциального поставщика (подрядчика, исполнителя) представляются сметы в целом по организации и по каждому такому подразделению.
A37: 2 В случае если этапы НИР (ОКР) выполняются в одном году, то формы, содержащие информацию о финансово-хозяйственной деятельности организации в целом (формы №№ 8 (8д), 10 (10д), 11 (11д), 12 (12д), 13 (13д), 21, 21д, 22 (22д), 23, 23д приложения № 5 к настоящему приказу), представляются единожды в составе соответствующего предложения о цене.
A38: 3 Представляются по статьям затрат согласно Порядку.
A39: 4 При проведении процедуры перевода в фиксированную цену других видов цен на продукцию организацией с учетом установленных в государственном контракте (контракте) условий уточнения и порядка перевода соответствующего вида цены на продукцию в фиксированную цену в графах 8-9 представляются планируемые затраты года окончания поставки продукции в рамках выполнения государственного контракта (контракта) (или завершения отдельных этапов поставки продукции, если государственным контрактом (контрактом) предусмотрены такие этапы). В случае если технологический цикл производства продукции составляет более 1 года либо год начала производства продукции не соответствует году окончания ее производства и поставки (или завершения отдельных этапов поставки продукции, если государственным контрактом (контрактом) предусмотрены такие этапы), то организация представляет сведения о затратах по годам, предшествующим году поставки продукции, в соответствии с графами 3-6 на каждый год производства продукции, дополнив форму после графы 6 графами, аналогичными по содержанию графам 3-6 соответственно (с последующей корректировкой нумерации граф), для указания информации.
A40: 5 В пояснительной записке, прилагаемой к соответствующему предложению о цене, организацией представляется обоснование применяемого индекса цен (в случае использования).
A41: 6 Указывается метод распределения затрат согласно Порядку.
A43: Используемые сокращения и их расшифровка:
B44: ГОЗ – государственный оборонный заказ; НИР (ОКР) – научно-исследовательская работа (опытно-конструкторская работа).

Sheet 21 свед. об V поставки (25-27)
V1: Форма № 21
B3: Сведения об объемах поставки продукции, в том числе по государственному оборонному заказу, включая экспортные поставки
B4: ФГАОУ ВО «Санкт-Петербургский политехнический университет Петра Великого»
A5: (наименование организации-поставщика (подрядчика, исполнителя))
A7: № строки | B7: Наименование | C7: Единица измерения | D7: Отчет за n-ый год (2024 г.) | L7: Предусмотрено бизнес-планом на 2025 г. | P7: Предусмотрено бизнес-планом на 2026 г. | T7: Предусмотрено бизнес-планом на 2027 г.
D8: в целом по предприятию | H8: в том числе по государственным контрактам (контрактам) ГОЗ | L8: в целом по предприятию | N8: в том числе по государственным контрактам (контрактам) ГОЗ | P8: в целом по предприятию | R8: в том числе по государственным контрактам (контрактам) ГОЗ | T8: в целом по предприятию | V8: в том числе по государственным контрактам (контрактам) ГОЗ
D9: план | E9: в том числе на экспорт | F9: факт | G9: в том числе на экспорт | H9: план | I9: в том числе на экспорт | J9: факт | K9: в том числе на экспорт | L9: план | M9: в том числе на экспорт | N9: план | O9: в том числе на экспорт | P9: план | Q9: в том числе на экспорт | R9: план | S9: в том числе на экспорт | T9: план | U9: в том числе на экспорт | V9: план | W9: в том числе на экспорт
A10: 1 | B10: 2 | C10: 3 | D10: 4 | E10: 5 | F10: 6 | G10: 7 | H10: 8 | I10: 9 | J10: 10 | K10: 11 | L10: 12 | M10: 13 | N10: 14 | O10: 15 | P10: 16 | Q10: 17 | R10: 18 | S10: 19 | T10: 20 | U10: 21 | V10: 22 | W10: 23
A11: 1. | B11: Выручка (нетто) от реализации продукции (без НДС) | C11: тыс. руб. | D11: 0 | E11: Х | F11: 0 | G11: Х | H11: 0 | I11: Х | J11: 0 | K11: Х | L11: 0 | M11: Х | N11: 0 | O11: Х | P11: 0 | Q11: Х | R11: 0 | S11: Х | T11: 0 | U11: Х | V11: 0 | W11: Х
A12: 2. | B12: Финансовый результат (+ прибыль/ - убыток) от реализации продукции | C12: тыс. руб. | D12: =D11-D22 | E12: Х | F12: =F11-F22 | G12: Х | H12: X | I12: Х | J12: X | K12: Х | L12: =L11-L22 | M12: Х | N12: X | O12: Х | P12: =P11-P22 | Q12: Х | R12: X | S12: Х | T12: =T11-T22 | U12: Х | V12: X | W12: Х
A13: 2.1 | B13: валовая прибыль (убыток) | C13: тыс. руб. | D13: 0 | E13: Х | G13: Х | H13: X | I13: Х | J13: X | K13: Х | M13: Х | N13: X | O13: Х | Q13: Х | R13: X | S13: Х | U13: Х | V13: X | W13: Х
A14: 2.2 | B14: прибыль (убыток) от продаж | C14: тыс. руб. | D14: 0 | E14: Х | G14: Х | H14: X | I14: Х | J14: X | K14: Х | M14: Х | N14: X | O14: Х | Q14: Х | R14: X | S14: Х | U14: Х | V14: X | W14: Х
A15: 2.3 | B15: прибыль (убыток) до налогообложения | C15: тыс. руб. | D15: =D12 | E15: Х | F15: 0 | G15: Х | H15: X | I15: Х | J15: X | K15: Х | L15: =L12 | M15: Х | N15: X | O15: Х | P15: =P12 | Q15: Х | R15: X | S15: Х | T15: =T12 | U15: Х | V15: X | W15: Х
A16: 2.4 | B16: чистая прибыль (убыток) | C16: тыс. руб. | D16: =D15*0.8 | E16: Х | F16: 0 | G16: Х | H16: X | I16: Х | J16: X | K16: Х | L16: 0 | M16: Х | N16: X | O16: Х | P16: 0 | Q16: Х | R16: X | S16: Х | T16: 0 | U16: Х | V16: X | W16: Х
A17: 3. | B17: Уровень рентабельности | E17: Х | G17: Х | H17: X | I17: Х | J17: X | K17: Х | M17: Х | N17: X | O17: Х | Q17: Х | R17: X | S17: Х | U17: Х | V17: X | W17: Х
A18: 3.1 | B18: строка 2.1 / строка 4 | C18: % | D18: =D13/D22 | E18: Х | G18: Х | H18: X | I18: Х | J18: X | K18: Х | M18: Х | N18: X | O18: Х | Q18: Х | R18: X | S18: Х | U18: Х | V18: X | W18: Х
A19: 3.2 | B19: строка 2.2 / строка 4 | C19: % | D19: =D14/D22 | E19: Х | G19: Х | H19: X | I19: Х | J19: X | K19: Х | M19: Х | N19: X | O19: Х | Q19: Х | R19: X | S19: Х | U19: Х | V19: X | W19: Х
A20: 3.3 | B20: строка 2.3 / строка 4 | C20: % | D20: =D15/D22*100 | E20: Х | F20: =F15/F22*100 | G20: Х | H20: X | I20: Х | J20: X | K20: Х | L20: =L15/L22*100 | M20: Х | N20: X | O20: Х | P20: =P15/P22*100 | Q20: Х | R20: X | S20: Х | T20: =T15/T22*100 | U20: Х | V20: X | W20: Х
A21: 3.4 | B21: строка 2.4 / строка 4 | C21: % | D21: =D16/D22*100 | E21: Х | F21: =F16/F22*100 | G21: Х | H21: X | I21: Х | J21: X | K21: Х | L21: =L16/L22*100 | M21: Х | N21: X | O21: Х | P21: =P16/P22*100 | Q21: Х | R21: X | S21: Х | T21: =T16/T22*100 | U21: Х | V21: X | W21: Х
A22: 4. | B22: Себестоимость реализованной продукции | C22: тыс. руб. | D22: 0 | E22: Х | F22: 0 | G22: Х | H22: 0 | I22: Х | J22: 0 | K22: Х | L22: 0 | M22: Х | N22: 0 | O22: Х | P22: 0 | Q22: Х | R22: 0 | S22: Х | T22: 0 | U22: Х | V22: 0 | W22: Х
A23: 5. | B23: Себестоимость товарной продукции | C23: тыс. руб. | D23: 0 | E23: Х | F23: 0 | G23: Х | H23: 0 | I23: Х | J23: 0 | K23: Х | L23: 0 | M23: Х | N23: =J23-J22+N22 | O23: Х | P23: 0 | Q23: Х | R23: =N23-N22+R22 | S23: Х | T23: 0 | U23: Х | V23: =R23-R22+V22 | W23: Х
A24: 6. | B24: Среднесписочная численность работников предприятия, всего | C24: чел. | D24: =D26+D35 | E24: Х | F24: =F26+F35 | G24: Х | H24: =H26+H35 | I24: Х | J24: =J26+J35 | K24: Х | L24: =L26+L35 | M24: Х | N24: =N26+N35 | O24: Х | P24: =P26+P35 | Q24: Х | R24: =R26+R35 | S24: Х | T24: =T26+T35 | U24: Х | V24: =V26+V35 | W24: Х
B25: в том числе:
A26: 6.1 | B26: среднесписочная численность основных работников: | C26: чел. | D26: =D29+D30+D31 | E26: Х | F26: =F29+F30+F31 | G26: Х | H26: =H29+H30+H31 | I26: Х | J26: =J29+J30+J31 | K26: Х | L26: =L29+L30+L31 | M26: Х | N26: =N29+N30+N31 | O26: Х | P26: =P29+P30+P31 | Q26: Х | R26: =R29+R30+R31 | S26: Х | T26: =T29+T30+T31 | U26: Х | V26: =V29+V30+V31 | W26: Х
B27: - рабочие-сдельщики; | D27: Х | E27: Х | F27: Х | G27: Х | H27: Х | I27: Х | J27: Х | K27: Х | L27: Х | M27: Х | N27: Х | O27: Х | P27: Х | Q27: Х | R27: Х | S27: Х | T27: Х | U27: Х | V27: Х | W27: Х
B28: - рабочие-повременщики; | D28: Х | E28: Х | F28: Х | G28: Х | H28: Х | I28: Х | J28: Х | K28: Х | L28: Х | M28: Х | N28: Х | O28: Х | P28: Х | Q28: Х | R28: Х | S28: Х | T28: Х | U28: Х | V28: Х | W28: Х
B29: - прочие категории | D29: 0 | E29: Х | F29: 0 | G29: Х | H29: 0 | I29: Х | J29: 0 | K29: Х | L29: 0 | M29: Х | N29: 0 | O29: Х | P29: 0 | Q29: Х | R29: 0 | S29: Х | T29: 0 | U29: Х | V29: 0 | W29: Х
B30: - научные, инженерные и технические работники | D30: 0 | E30: Х | F30: 0 | G30: Х | H30: 0 | I30: Х | J30: 0 | K30: Х | L30: 0 | M30: Х | N30: 0 | O30: Х | P30: 0 | Q30: Х | R30: 0 | S30: Х | T30: 0 | U30: Х | V30: 0 | W30: Х
B31: - профессорско-преподавательский состав | D31: 0 | E31: Х | F31: 0 | G31: Х | H31: 0 | I31: Х | J31: 0 | K31: Х | L31: 0 | M31: Х | N31: 0 | O31: Х | P31: 0 | Q31: Х | R31: 0 | S31: Х | T31: 0 | U31: Х | V31: 0 | W31: Х
A32: 6.2 | B32: среднесписочная численность работников, относящихся к общепроизводственным затратам: | C32: чел. | D32: Х | E32: Х | F32: Х | G32: Х | H32: Х | I32: Х | J32: Х | K32: Х | L32: Х | M32: Х | N32: Х | O32: Х | P32: Х | Q32: Х | R32: Х | S32: Х | T32: Х | U32: Х | V32: Х | W32: Х
B33: - административно-управленческий персонал; | D33: Х | E33: Х | F33: Х | G33: Х | H33: Х | I33: Х | J33: Х | K33: Х | L33: Х | M33: Х | N33: Х | O33: Х | P33: Х | Q33: Х | R33: Х | S33: Х | T33: Х | U33: Х | V33: Х | W33: Х
B34: - вспомогательные работники | D34: Х | E34: Х | F34: Х | G34: Х | H34: Х | I34: Х | J34: Х | K34: Х | L34: Х | M34: Х | N34: Х | O34: Х | P34: Х | Q34: Х | R34: Х | S34: Х | T34: Х | U34: Х | V34: Х | W34: Х
A35: 6.3 | B35: среднесписочная численность работников, относящихся к общехозяйственным затратам / административно-управленческим расходам: | C35: чел. | D35: =D36+D37 | E35: Х | F35: =F36+F37 | G35: Х | H35: =H36+H37 | I35: Х | J35: =J36+J37 | K35: Х | L35: =L36+L37 | M35: Х | N35: =N36+N37 | O35: Х | P35: =P36+P37 | Q35: Х | R35: =R36+R37 | S35: Х | T35: =T36+T37 | U35: Х | V35: =V36+V37 | W35: Х
B36: - административно-управленческий персонал; | D36: 0 | E36: Х | F36: 0 | G36: Х | H36: 0 | I36: Х | J36: 0 | K36: Х | L36: 0 | M36: Х | N36: 0 | O36: Х | P36: 0 | Q36: Х | R36: 0 | S36: Х | T36: 0 | U36: Х | V36: 0 | W36: Х
B37: - вспомогательные работники | D37: 0 | E37: Х | F37: 0 | G37: Х | H37: 0 | I37: Х | J37: 0 | K37: Х | L37: 0 | M37: Х | N37: 0 | O37: Х | P37: 0 | Q37: Х | R37: 0 | S37: Х | T37: 0 | U37: Х | V37: 0 | W37: Х
A38: 7.4 | B38: Основная заработная плата работников предприятия, всего: | C38: тыс. руб. | D38: =D40+D49 | E38: Х | F38: =F40+F49 | G38: Х | H38: =H40+H49 | I38: Х | J38: =J40+J49 | K38: Х | L38: =L40+L49 | M38: Х | N38: =N40+N49 | O38: Х | P38: =P40+P49 | Q38: Х | R38: =R40+R49 | S38: Х | T38: =T40+T49 | U38: Х | V38: =V40+V49 | W38: Х
B39: в том числе:
A40: 7.1 | B40: основные работники: | C40: тыс. руб. | D40: =D43+D44+D45 | E40: Х | F40: =F43+F44+F45 | G40: Х | H40: =H43+H44+H45 | I40: Х | J40: =J43+J44+J45 | K40: Х | L40: =L43+L44+L45 | M40: Х | N40: =N43+N44+N45 | O40: Х | P40: =P43+P44+P45 | Q40: Х | R40: =R43+R44+R45 | S40: Х | T40: =T43+T44+T45 | U40: Х | V40: =V43+V44+V45 | W40: Х
B41: - рабочие-сдельщики; | D41: Х | E41: Х | F41: Х | G41: Х | H41: Х | I41: Х | J41: Х | K41: Х | L41: Х | M41: Х | N41: Х | O41: Х | P41: Х | Q41: Х | R41: Х | S41: Х | T41: Х | U41: Х | V41: Х | W41: Х
B42: - рабочие-повременщики; | D42: Х | E42: Х | F42: Х | G42: Х | H42: Х | I42: Х | J42: Х | K42: Х | L42: Х | M42: Х | N42: Х | O42: Х | P42: Х | Q42: Х | R42: Х | S42: Х | T42: Х | U42: Х | V42: Х | W42: Х
B43: - прочие категории | D43: =ROUND(D29*D55/1000*11,2) | E43: Х | F43: 0 | G43: Х | H43: 0 | I43: Х | J43: 0 | K43: Х | L43: 0 | M43: Х | N43: 0 | O43: Х | P43: 0 | Q43: Х | R43: 0 | S43: Х | T43: 0 | U43: Х | V43: 0 | W43: Х
B44: - научные, инженерные и технические работники | D44: 0 | E44: Х | F44: 0 | G44: Х | H44: 0 | I44: Х | J44: 0 | K44: Х | L44: 0 | M44: Х | N44: 0 | O44: Х | P44: 0 | Q44: Х | R44: 0 | S44: Х | T44: 0 | U44: Х | V44: 0 | W44: Х
B45: - профессорско-преподавательский состав | D45: 0 | E45: Х | F45: 0 | G45: Х | H45: 0 | I45: Х | J45: 0 | K45: Х | L45: 0 | M45: Х | N45: 0 | O45: Х | P45: 0 | Q45: Х | R45: 0 | S45: Х | T45: 0 | U45: Х | V45: 0 | W45: Х
A46: 7.2 | B46: работники, относящиеся к общепроизводственным затратам: | C46: тыс. руб. | D46: Х | E46: Х | F46: Х | G46: Х | H46: Х | I46: Х | J46: Х | K46: Х | L46: Х | M46: Х | N46: Х | O46: Х | P46: Х | Q46: Х | R46: Х | S46: Х | T46: Х | U46: Х | V46: Х | W46: Х
B47: - административно-управленческий персонал; | D47: Х | E47: Х | F47: Х | G47: Х | H47: Х | I47: Х | J47: Х | K47: Х | L47: Х | M47: Х | N47: Х | O47: Х | P47: Х | Q47: Х | R47: Х | S47: Х | T47: Х | U47: Х | V47: Х | W47: Х
B48: - вспомогательные работники | D48: Х | E48: Х | F48: Х | G48: Х | H48: Х | I48: Х | J48: Х | K48: Х | L48: Х | M48: Х | N48: Х | O48: Х | P48: Х | Q48: Х | R48: Х | S48: Х | T48: Х | U48: Х | V48: Х | W48: Х
A49: 7.3 | B49: работники, относящиеся к общехозяйственным затратам / административно-управленческим расходам: | C49: тыс. руб. | D49: =D50+D51 | E49: Х | F49: =F50+F51 | G49: Х | H49: =H50+H51 | I49: Х | J49: =J50+J51 | K49: Х | L49: =L50+L51 | M49: Х | N49: =N50+N51 | O49: Х | P49: =P50+P51 | Q49: Х | R49: =R50+R51 | S49: Х | T49: =T50+T51 | U49: Х | V49: =V50+V51 | W49: Х
B50: - административно-управленческий персонал; | D50: 0 | E50: Х | F50: 0 | G50: Х | H50: 0 | I50: Х | J50: 0 | K50: Х | L50: 0 | M50: Х | N50: 0 | O50: Х | P50: 0 | Q50: Х | R50: 0 | S50: Х | T50: 0 | U50: Х | V50: 0 | W50: Х
B51: - вспомогательные работники | D51: 0 | E51: Х | F51: 0 | G51: Х | H51: 0 | I51: Х | J51: 0 | K51: Х | L51: 0 | M51: Х | N51: 0 | O51: Х | P51: 0 | Q51: Х | R51: 0 | S51: Х | T51: 0 | U51: Х | V51: 0 | W51: Х
A52: 8. | B52: Норматив основной заработной платы основных работников (стоимость человеко-месяц): | C52: руб.-месяц | D52: =ROUND(D40*1000/D26/11,0) | E52: Х | F52: =ROUND(F40*1000/F26/11,0) | G52: Х | H52: =ROUND(H40*1000/H76,0) | I52: Х | J52: =ROUND(J40*1000/J76,0) | K52: Х | L52: =ROUND(L40*1000/L26/11,0) | M52: Х | N52: =ROUND(N40*1000/N76,0) | O52: Х | P52: =ROUND(L52*1.04*1.057,0) | Q52: Х | R52: =ROUND(R40*1000/R76,0) | S52: Х | T52: =ROUND(P52*1.04*1.041,0) | U52: Х | V52: =ROUND(V40*1000/V76,0) | W52: Х
B53: - рабочие-сдельщики; | D53: Х | E53: Х | F53: Х | G53: Х | H53: Х | I53: Х | J53: Х | K53: Х | L53: Х | M53: Х | N53: Х | O53: Х | P53: Х | Q53: Х | R53: Х | S53: Х | T53: Х | U53: Х | V53: Х | W53: Х
B54: - рабочие-повременщики; | D54: Х | E54: Х | F54: Х | G54: Х | H54: Х | I54: Х | J54: Х | K54: Х | L54: Х | M54: Х | N54: Х | O54: Х | P54: Х | Q54: Х | R54: Х | S54: Х | T54: Х | U54: Х | V54: Х | W54: Х
B55: - прочие категории | D55: 0 | E55: Х | F55: 0 | G55: Х | H55: 0 | I55: Х | J55: 0 | K55: Х | L55: 0 | M55: Х | O55: Х | P55: 0 | Q55: Х | S55: Х | T55: 0 | U55: Х | W55: Х
B56: - научные, инженерные и технические работники | D56: 0 | E56: Х | F56: 0 | G56: Х | H56: 0 | I56: Х | J56: =J44*1000/J80 | K56: Х | L56: 0 | M56: Х | N56: =ROUNDUP(N44*1000/N80,2) | O56: Х | P56: 0 | Q56: Х | R56: =ROUND(R44*1000/R80,0) | S56: Х | T56: 0 | U56: Х | V56: =ROUND(V44*1000/V80,0) | W56: Х
B57: - профессорско-преподавательский состав | D57: 0 | E57: Х | F57: 0 | G57: Х | H57: 0 | I57: Х | J57: =IFERROR(J45*1000/J81,0) | K57: Х | L57: 0 | M57: Х | N57: =ROUND(N45*1000/N81,2) | O57: Х | P57: 0 | Q57: Х | R57: =IFERROR(ROUND(R45*1000/R81,2),0) | S57: Х | T57: 0 | U57: Х | V57: 0 | W57: Х
A58: 9.4 | B58: Дополнительная заработная плата работников предприятия, всего: | C58: тыс. руб. | D58: =D60+D69 | E58: Х | F58: =F60+F69 | G58: Х | H58: =H60+H69 | I58: Х | J58: =J60+J69 | K58: Х | L58: =L60+L69 | M58: Х | N58: =N60+N69 | O58: Х | P58: =P60+P69 | Q58: Х | R58: =R60+R69 | S58: Х | T58: =T60+T69 | U58: Х | V58: =V60+V69 | W58: Х
B59: в том числе:
A60: 9.1 | B60: основные работники: | C60: тыс. руб. | D60: =D63+D64+D65 | E60: Х | F60: =F63+F64+F65 | G60: Х | H60: =H63+H64+H65 | I60: Х | J60: =J63+J64+J65 | K60: Х | L60: =L63+L64+L65 | M60: Х | N60: =N63+N64+N65 | O60: Х | P60: =P63+P64+P65 | Q60: Х | R60: =R63+R64+R65 | S60: Х | T60: =T63+T64+T65 | U60: Х | V60: =V63+V64+V65 | W60: Х
B61: - рабочие-сдельщики; | D61: Х | E61: Х | F61: Х | G61: Х | H61: Х | I61: Х | J61: Х | K61: Х | L61: Х | M61: Х | N61: Х | O61: Х | P61: Х | Q61: Х | R61: Х | S61: Х | T61: Х | U61: Х | V61: Х | W61: Х
B62: - рабочие-повременщики; | D62: Х | E62: Х | F62: Х | G62: Х | H62: Х | I62: Х | J62: Х | K62: Х | L62: Х | M62: Х | N62: Х | O62: Х | P62: Х | Q62: Х | R62: Х | S62: Х | T62: Х | U62: Х | V62: Х | W62: Х
B63: - прочие категории | D63: 0 | E63: Х | F63: 0 | G63: Х | H63: =H43*H73/100 | I63: Х | J63: 0 | K63: Х | L63: 0 | M63: Х | N63: 0 | O63: Х | P63: 0 | Q63: Х | R63: 0 | S63: Х | T63: 0 | U63: Х | V63: 0 | W63: Х
B64: - научные, инженерные и технические работники | D64: =D44*D74/100 | E64: Х | F64: 0 | G64: Х | H64: =H44*H74/100 | I64: Х | J64: 0 | K64: Х | L64: =ROUND(L44*L74/100,2) | M64: Х | N64: =N44*N74/100 | O64: Х | P64: =ROUND(P44*P74/100,2) | Q64: Х | R64: =R44*R74/100 | S64: Х | T64: =ROUND(T44*T74/100,2) | U64: Х | V64: =V44*V74/100 | W64: Х
B65: - профессорско-преподавательский состав | D65: =D45*D75/100 | E65: Х | F65: 0 | G65: Х | H65: =H45*H75/100 | I65: Х | J65: 0 | K65: Х | L65: =ROUND(L45*L75/100,2) | M65: Х | N65: =N45*N75/100 | O65: Х | P65: =ROUND(P45*P75/100,2) | Q65: Х | R65: =R45*R75/100 | S65: Х | T65: =ROUND(T45*T75/100,2) | U65: Х | V65: =V45*V75/100 | W65: Х
A66: 9.2 | B66: работники, относящиеся к общепроизводственным затратам: | C66: тыс. руб. | D66: Х | E66: Х | F66: Х | G66: Х | H66: Х | I66: Х | J66: Х | K66: Х | L66: Х | M66: Х | N66: Х | O66: Х | P66: Х | Q66: Х | R66: Х | S66: Х | T66: Х | U66: Х | V66: Х | W66: Х
B67: - административно-управленческий персонал; | D67: Х | E67: Х | F67: Х | G67: Х | H67: Х | I67: Х | J67: Х | K67: Х | L67: Х | M67: Х | N67: Х | O67: Х | P67: Х | Q67: Х | R67: Х | S67: Х | T67: Х | U67: Х | V67: Х | W67: Х
B68: - вспомогательные работники | D68: Х | E68: Х | F68: Х | G68: Х | H68: Х | I68: Х | J68: Х | K68: Х | L68: Х | M68: Х | N68: Х | O68: Х | P68: Х | Q68: Х | R68: Х | S68: Х | T68: Х | U68: Х | V68: Х | W68: Х
A69: 9.3 | B69: работники, относящиеся к общехозяйственным затратам / административно-управленческим расходам: | C69: тыс. руб. | D69: =D70+D71 | E69: Х | F69: =F70+F71 | G69: Х | H69: =H70+H71 | I69: Х | J69: =J70+J71 | K69: Х | L69: =L70+L71 | M69: Х | N69: =N70+N71 | O69: Х | P69: =P70+P71 | Q69: Х | R69: =R70+R71 | S69: Х | T69: =T70+T71 | U69: Х | V69: =V70+V71 | W69: Х
B70: - административно-управленческий персонал; | D70: =D50*D73/100 | E70: Х | F70: 0 | G70: Х | H70: 0 | I70: Х | J70: 0 | K70: Х | L70: =L50*L74/100 | M70: Х | N70: =N50*N74/100 | O70: Х | P70: =P50*P74/100 | Q70: Х | R70: =R50*R74/100 | S70: Х | T70: =T50*T74/100 | U70: Х | V70: =V50*V74/100 | W70: Х
B71: - вспомогательные работники | D71: 0 | E71: Х | F71: 0 | G71: Х | H71: 0 | I71: Х | J71: 0 | K71: Х | L71: 0 | M71: Х | N71: 0 | O71: Х | P71: 0 | Q71: Х | R71: 0 | S71: Х | T71: 0 | U71: Х | V71: 0 | W71: Х
A72: 10. | B72: Норматив дополнительной заработной платы основных работников | C72: % | D72: =D60/D40*100 | E72: Х | F72: =F60/F40*100 | G72: Х | H72: =H60/H40*100 | I72: Х | J72: =J60/J40*100 | K72: Х | L72: =L60/L40*100 | M72: Х | N72: =N60/N40*100 | O72: Х | P72: =P60/P40*100 | Q72: Х | R72: =R60/R40*100 | S72: Х | T72: =T60/T40*100 | U72: Х | V72: =V60/V40*100 | W72: Х
B73: - прочие категории | D73: 8.6866 | F73: 0 | H73: 0 | J73: 0 | L73: 0 | N73: 0 | P73: 0 | R73: 0 | T73: 0 | V73: 0
B74: - научные, инженерные и технические работники | D74: 8.6866 | F74: =F64/F44*100 | H74: 8.6866 | J74: =IFERROR(J64/J44*100,0) | L74: 8.6866 | N74: 8.6866 | P74: 8.6866 | R74: 8.6866 | T74: 8.6866 | V74: 8.6866
B75: - профессорско-преподавательский состав | D75: 19.1091 | F75: =F65/F45*100 | H75: 19.1091 | J75: =IFERROR(J65/J45*100,0) | L75: 19.1091 | N75: 19.1091 | P75: 19.1091 | R75: 19.1091 | T75: 19.1091 | V75: 19.1091
A76: 11.4 | B76: Технологическая трудоемкость, всего | C76: человеко-месяц | D76: =D40*1000/D52 | E76: Х | F76: =ROUND(F40*1000/F52,0) | G76: Х | H76: =H80+H81 | I76: Х | J76: =J80+J81 | K76: Х | L76: =L40*1000/L52 | M76: Х | N76: =N80+N81 | O76: Х | P76: =P40*1000/P52 | Q76: Х | R76: =R80+R81 | S76: Х | T76: =T40*1000/T52 | U76: Х | V76: =V80+V81 | W76: Х
B77: в том числе:
A78: 11.1 | B78: - рабочие-сдельщики; | D78: Х | E78: Х | F78: Х | G78: Х | H78: Х | I78: Х | J78: Х | K78: Х | L78: Х | M78: Х | N78: Х | O78: Х | P78: Х | Q78: Х | R78: Х | S78: Х | T78: Х | U78: Х | V78: Х | W78: Х
A79: 11.2 | B79: - рабочие-повременщики; | D79: Х | E79: Х | F79: Х | G79: Х | H79: Х | I79: Х | J79: Х | K79: Х | L79: Х | M79: Х | N79: Х | O79: Х | P79: Х | Q79: Х | R79: Х | S79: Х | T79: Х | U79: Х | V79: Х | W79: Х
A80: 11.3 | B80: - научные, инженерные и технические работники | D80: =D44*1000/D56 | E80: Х | F80: =F44*1000/F56 | G80: Х | H80: 789.313 | I80: Х | J80: 458.947 | K80: Х | L80: =L44*1000/L56 | M80: Х | N80: 649.424 | O80: Х | P80: =P44*1000/P56 | Q80: Х | R80: 428.086 | S80: Х | T80: =T44*1000/T56 | U80: Х | V80: 431.3 | W80: Х
A81: 11.4 | B81: - профессорско-преподавательский состав | D81: =D45*1000/D57 | E81: Х | F81: =F45*1000/F57 | G81: Х | H81: 20.7 | I81: Х | J81: 26.435 | K81: Х | L81: =L45*1000/L57 | M81: Х | N81: 11.51 | O81: Х | P81: =P45*1000/P57 | Q81: Х | R81: 0 | S81: Х | T81: =T45*1000/T57 | U81: Х | V81: 0 | W81: Х
A82: 12.4 | B82: Общепроизводственные затраты | C82: тыс. руб. | D82: Х | E82: Х | F82: Х | G82: Х | H82: Х | I82: Х | J82: Х | K82: Х | L82: Х | M82: Х | N82: Х | O82: Х | P82: Х | Q82: Х | R82: Х | S82: Х | T82: Х | U82: Х | V82: Х | W82: Х
A83: 12.1 | B83: База распределения общепроизводственных затрат (_________________________) | C83: тыс. руб. | D83: Х | E83: Х | F83: Х | G83: Х | H83: Х | I83: Х | J83: Х | K83: Х | L83: Х | M83: Х | N83: Х | O83: Х | P83: Х | Q83: Х | R83: Х | S83: Х | T83: Х | U83: Х | V83: Х | W83: Х
A84: 12.2 | B84: Норматив общепроизводственных затрат | C84: % | D84: Х | E84: Х | F84: Х | G84: Х | H84: Х | I84: Х | J84: Х | K84: Х | L84: Х | M84: Х | N84: Х | O84: Х | P84: Х | Q84: Х | R84: Х | S84: Х | T84: Х | U84: Х | V84: Х | W84: Х
A85: 13.4 | B85: Общехозяйственные затраты / административно-управленческие расходы | C85: тыс. руб. | D85: 0 | E85: Х | F85: 0 | G85: Х | H85: 0 | I85: Х | J85: 0 | K85: Х | L85: 0 | M85: Х | N85: 0 | O85: Х | P85: 0 | Q85: Х | R85: 0 | S85: Х | T85: 0 | U85: Х | V85: 0 | W85: Х
A86: 13.1 | B86: База распределения общехозяйственных затрат / административно-управленческих расходов (основная заработная плата работников) | C86: тыс. руб. | D86: =D40 | E86: Х | F86: =F40 | G86: Х | H86: =H40 | I86: Х | J86: =J40 | K86: Х | L86: =L40 | M86: Х | N86: =N40 | O86: Х | P86: =P40 | Q86: Х | R86: =R40 | S86: Х | T86: =T40 | U86: Х | V86: =V40 | W86: Х
A87: 13.2 | B87: Норматив общехозяйственных затрат / административно-управленческих расходов | C87: % | D87: =D85/D86*100 | E87: Х | F87: =F85/F86*100 | G87: Х | H87: =H85/H86*100 | I87: Х | J87: =J85/J86*100 | K87: Х | L87: =L85/L86*100 | M87: Х | N87: =N85/N86*100 | O87: Х | P87: =P85/P86*100 | Q87: Х | R87: =R85/R86*100 | S87: Х | T87: =T85/T86*100 | U87: Х | V87: =V85/V86*100 | W87: Х
A88: 14. | B88: Норматив транспортно-заготовительных затрат | C88: % | D88: Х | E88: Х | F88: Х | G88: Х | H88: Х | I88: Х | J88: Х | K88: Х | L88: Х | M88: Х | N88: Х | O88: Х | P88: Х | Q88: Х | R88: Х | S88: Х | T88: Х | U88: Х | V88: Х | W88: Х
A89: 15. | B89: Норматив коммерческих (внепроизводственных) затрат | C89: % | D89: Х | E89: Х | F89: Х | G89: Х | H89: Х | I89: Х | J89: Х | K89: Х | L89: Х | M89: Х | N89: Х | O89: Х | P89: Х | Q89: Х | R89: Х | S89: Х | T89: Х | U89: Х | V89: Х | W89: Х
B91: Начальник ОФЭАУ НИОКР | P91: Главный бухгалтер ФГАОУ ВО «СПбПУ»
B92: __________________________ Н.О. Васецкая | P92: __________________________ Н.В. Иванова
B93: (подпись) (Ф.И.О.) | P93: (подпись) (Ф.И.О.)
B94: «____» __________________ 2026 г. | P94: «____» __________________ 2026 г.
A96: 1 Указанная форма заполняется в случае применения одного из следующих методов определения цены на продукцию: затратного метода, метода индексации базовой цены или метода индексации по статьям затрат, предусмотренных Положением о государственном регулировании цен на продукцию, поставляемую по государственному оборонному заказу, утвержденного постановлением Правительства Российской Федерации от 2 декабря 2017 года № 1465. В случае если этапы НИР (ОКР) выполняются в одном году, то формы, содержащие информацию о финансово-хозяйственной деятельности организации в целом (формы №№ 8 (8д), 10 (10д), 11 (11д), 12 (12д), 13 (13д), 21, 21д, 22 (22д), 23, 23д приложения № 5 к настоящему приказу), представляются единожды в составе соответствующего предложения о цене.
A97: 2 При проведении процедуры перевода в фиксированную цену других видов цен на продукцию организацией с учетом установленных в государственном контракте (контракте) условий уточнения и порядка перевода соответствующего вида цены на продукцию в фиксированную цену в графах 12-15 представляются планируемые затраты года окончания поставки продукции в рамках выполнения государственного контракта (контракта) (или завершения отдельных этапов поставки продукции, если государственным контрактом (контрактом) предусмотрены такие этапы). В случае если технологический цикл производства продукции составляет более 1 года либо год начала производства продукции не соответствует году окончания ее производства и поставки (или завершения отдельных этапов поставки продукции, если государственным контрактом (контрактом) предусмотрены такие этапы), то организация представляет сведения о затратах по годам, предшествующим году поставки продукции, в соответствии с графами 4-11 на каждый год производства продукции, дополнив форму после графы 11 графами, аналогичными по содержанию графам 4-11 соответственно (с последующей корректировкой нумерации граф), для указания информации.
A98: 3 К основным работникам относятся основные производственные рабочие, инженерно-технические и другие категории работников, непосредственно участвующие в процессе производства продукции, согласно порядку определения состава затрат, включаемых в цену продукции, поставляемой в рамках государственного оборонного заказа, утвержденному в соответствии с постановлением Правительства Российской Федерации от 2 декабря 2017 года № 1465 "О государственном регулировании цен на продукцию, поставляемую по государственному оборонному заказу, а также о внесении изменений и признании утратившими силу некоторых актов Правительства Российской Федерации" (далее - Порядок).
A99: 4 Заполняется с учетом незавершенного производства в соответствии с учетной политикой организации.
A100: 5 Указывается используемая единица измерения трудоемкости: нормо-час / человеко-час / человеко-день / человеко-месяц.
A101: 6 Указывается используемая единица измерения: руб.-час / руб.-день / руб.-месяц.
A102: 7 Указывается метод распределения затрат согласно Порядку.
A104: Используемые сокращения и их расшифровка:
B105: ГОЗ – государственный оборонный заказ; НДС – налог на добавленную стоимость; НИР (ОКР) – научно-исследовательская работа (опытно-конструкторская работа).

Sheet 23 труд (25-27)
AA1: Форма № 23
A3: Расчет (обоснование) трудоемкости
A4: по договорам в рамках государственного оборонного заказа ФГАОУ ВО «СПбПУ» на период 2025-2027 гг
A6: № п/п | B6: Наименование товаров, работ, услуг | C6: Отчетный период / период, предшествующий планируемому (год 2024) | M6: Планируемый период (год 2025) | R6: Планируемый период (год 2026) | W6: Планируемый период (год 2027)
C7: план | H7: факт
C8: технологическая трудоемкость единицы продукции (человеко-месяц) | D8: стоимость руб.-месяц (руб.) | E8: годовой объем производства (штуки) | F8: технологическая трудоемкость всего (гр.3*гр.5) | G8: основная заработная плата основных работников (гр.4*гр.6) | H8: технологическая трудоемкость единицы продукции (человеко-месяц) | I8: стоимость руб.-месяц (руб.) | J8: годовой объем производства (штуки) | K8: технологическая трудоемкость всего (гр.8*гр.10) | L8: основная заработная плата основных работников9 (гр.9*гр.11) | M8: технологическая трудоемкость единицы продукции (человеко-месяц) | N8: стоимость руб.-месяц (руб.) | O8: годовой объем производства (штуки) | P8: технологическая трудоемкость всего (гр.13*гр.15) | Q8: основная заработная плата основных работников9 (гр.14*гр.16) | R8: технологическая трудоемкость единицы продукции (человеко-месяц6) | S8: стоимость руб.-месяц (руб.) | T8: годовой объем производства (штуки) | U8: технологическая трудоемкость всего (гр.13*гр.15) | V8: основная заработная плата основных работников (гр.14*гр.16) | W8: технологическая трудоемкость единицы продукции (человеко-месяц) | X8: стоимость руб.-месяц (руб.) | Y8: годовой объем производства (штуки) | Z8: технологическая трудоемкость всего (гр.13*гр.15) | AA8: основная заработная плата основных работников (гр.14*гр.16)
A9: 1 | B9: 2 | C9: 3 | D9: 4 | E9: 5 | F9: 6 | G9: 7 | H9: 8 | I9: 9 | J9: 10 | K9: 11 | L9: 12 | M9: 13 | N9: 14 | O9: 15 | P9: 16 | Q9: 17 | R9: 18 | S9: 19 | T9: 20 | U9: 21 | V9: 22 | W9: 18 | X9: 19 | Y9: 20 | Z9: 21 | AA9: 22
B10: ТЕМА | C10: 0 | D10: 0 | E10: 0 | F10: 0 | G10: 0 | H10: 0 | I10: 0 | J10: 0 | K10: 0 | L10: 0 | M10: 0 | N10: 0 | O10: 0 | P10: 0 | Q10: 0 | R10: 0 | S10: =IFERROR(ROUND(V10/U10,2),0) | T10: 0 | U10: =R10*T10 | V10: 0 | W10: 0 | X10: =IFERROR(ROUND(AA10/Z10,2),0) | Y10: 0 | Z10: =W10*Y10 | AA10: 0
B11: План работ по договорам в рамках ГОЗ (по предварительным данным от подразделений) | C11: 0 | D11: =ROUND(G11/F11,2) | F11: =C11 | G11: 0 | H11: 0 | I11: =ROUND(L11/K11,2) | K11: =H11 | L11: 0 | M11: 0 | N11: =ROUND(Q11/P11,2) | P11: =M11 | Q11: 0 | R11: 0 | S11: =ROUND(V11/U11,2) | U11: =R11 | V11: 0 | W11: 0 | X11: =ROUND(AA11/Z11,2) | Z11: =W11 | AA11: 0
A12: ИТОГО по ГОЗ | C12: =SUM(C10:C11) | D12: =G12/F12 | F12: =SUM(F10:F11) | G12: =SUM(G10:G11) | H12: =SUM(H10:H11) | I12: =ROUND(L12/K12,0) | K12: =SUM(K10:K11) | L12: =SUM(L10:L11) | M12: =SUM(M10:M11) | N12: =ROUND(Q12/P12,0) | P12: =SUM(P10:P11) | Q12: =SUM(Q10:Q11) | R12: =SUM(R10:R11) | S12: =ROUND(V12/U12,0) | U12: =SUM(U10:U11) | V12: =SUM(V10:V11) | W12: =SUM(W10:W11) | X12: =ROUND(AA12/Z12,0) | Z12: =SUM(Z10:Z11) | AA12: =SUM(AA10:AA11)
A13: 1. | B13: План работ по договорам, источником финансирования которых, являются средства от приносящей доход деятельности | C13: 0 | D13: =ROUNDUP(G13/F13,2) | F13: =C13 | G13: 0 | H13: 0 | I13: =L13/K13 | K13: =H13 | L13: 0 | M13: 0 | N13: =Q13/P13 | P13: =M13 | Q13: 0 | R13: 0 | S13: =V13/U13 | U13: =R13 | V13: 0 | W13: 0 | X13: =AA13/Z13 | Z13: =W13 | AA13: 0
A14: ИТОГО прочая продукция | C14: =C13 | D14: =ROUNDUP(G14/F14,2) | F14: =F13 | G14: =G13 | H14: =H13 | I14: =L14/K14 | K14: =K13 | L14: =L13 | M14: =M13 | N14: =Q14/P14 | P14: =P13 | Q14: =Q13 | R14: =R13 | S14: =V14/U14 | U14: =U13 | V14: =V13 | W14: =W13 | X14: =AA14/Z14 | Z14: =Z13 | AA14: =AA13
A15: ВСЕГО | C15: =C12+C14 | D15: =G15/F15 | F15: =F12+F14 | G15: =G12+G14 | H15: =H12+H14 | I15: =ROUND(L15/K15,0) | K15: =K12+K14 | L15: =L12+L14 | M15: =M12+M14 | N15: =ROUND(Q15/P15,0) | P15: =P12+P14 | Q15: =Q12+Q14 | R15: =R12+R14 | S15: =ROUND(V15/U15,0) | U15: =U12+U14 | V15: =V12+V14 | W15: =W12+W14 | X15: =ROUND(AA15/Z15,0) | Z15: =Z12+Z14 | AA15: =AA12+AA14
C17: Проректор по научной работе | R17: Начальник ОФЭиАУ НИОКР
C18: _____________________ Ю.В. Фомин | R18: ___________________ Н.О. Васецкая
C19: (подпись) (Ф.И.О.) | R19: (подпись) (Ф.И.О.)
C20: «____» __________________ 2026 г. | R20: «____» __________________ 2026 г.
A22: 1 Указанный документ обязателен для представления следующими организациями: - головными исполнителями; - исполнителями, поставляющими головному исполнителю покупные комплектующие изделия (полуфабрикаты) и работы (услуги) производственного характера, связанные с поставкой продукции в течение планового периода, по каждой номенклатурной позиции комплектующих изделий (полуфабрикатов) и работ (услуг), расходы на закупку которой составляют не менее 10 процентов суммарных расходов на закупку покупных комплектующих изделий (полуфабрикатов), работ (услуг) производственного характера и не менее одного миллиона рублей либо не менее 5 процентов указанных суммарных расходов, если они составляют один миллиард рублей и более; - исполнителями, выполняющими работы (услуги) по отдельным этапам (составным частям) научно-исследовательских, опытно-конструкторских и других работ. Иными исполнителями, участвующими в поставках продукции по государственному оборонному заказу, указанный документ представляется по дополнительному запросу государственного заказчика, отраслевого органа, Федеральной антимонопольной службы. Сведения в рамках расчета (обоснования) трудоемкости представляются с соблюдением требований законодательства Российской Федерации о государственной тайне.
A23: 2 Заполняется в случае если распределение общепроизводственных и общехозяйственных затрат / административно-управленческих расходов осуществляется пропорционально основной заработной плате основных работников. Если распределение осуществляется иным методом, организацией представляется расчет обоснование иной базы распределения общепроизводственных и общехозяйственных затрат / административно-управленческих расходов, в произвольной форме, отражающей информацию за отчетный период / период, предшествующий планируемому (по плановым и фактическим показателям), и плановый период.
A24: 3 В случае если этапы НИР (ОКР) выполняются в одном году, то формы, содержащие информацию о финансово-хозяйственной деятельности организации в целом (формы №№ 8 (8д), 10 (10д), 11 (11д), 12 (12д), 13 (13д), 21, 21д, 22 (22д), 23, 23д приложения № 5 к настоящему приказу), представляются единожды в составе соответствующего предложения о цене.
A25: 4 Заполняется с учетом незавершенного производства.
A26: 5 При проведении процедуры перевода в фиксированную цену других видов цен на продукцию организацией с учетом установленных в государственном контракте (контракте) условий уточнения и порядка перевода соответствующего вида цены на продукцию в фиксированную цену в графах 3-12 представляются затраты по состоянию на конкретную дату, планируемые затраты до окончания поставки продукции в рамках выполнения государственного контракта (контракта) (или завершения отдельных этапов поставки продукции, если государственным контрактом (контрактом) предусмотрены такие этапы) представляются в графах 13-17. В случае если технологический цикл производства продукции составляет более 1 года либо год начала производства продукции не соответствует году окончания ее производства и поставки (или завершения отдельных этапов поставки продукции, если государственным контрактом (контрактом) предусмотрены такие этапы), то организация представляет сведения о затратах по состоянию на конкретную дату в соответствии с графами 3-12 по годам, дополнив форму после графы 12 графами, аналогичными по содержанию графам 3-12 соответственно (с последующей корректировкой нумерации граф), на каждый год производства продукции для указания информации.
A27: 6 Указывается используемая единица измерения трудоемкости: нормо-час / человеко-час / человеко-день / человеко-месяц.
A28: 7 Указывается используемая единица измерения: руб.-час / руб.-день / руб.-месяц.
A29: 8 При наличии незавершенного производства указывается в долях.
A30: 9 К основным работникам относятся основные производственные рабочие, инженерно-технические и другие категории работников, непосредственно участвующие в процессе производства продукции, согласно порядку определения состава затрат, включаемых в цену продукции, поставляемой в рамках государственного оборонного заказа, утвержденному в соответствии с постановлением Правительства Российской Федерации от 2 декабря 2017 года № 1465 "О государственном регулировании цен на продукцию, поставляемую по государственному оборонному заказу, а также о внесении изменений и признании утратившими силу некоторых актов Правительства Российской Федерации".
A32: Используемые сокращения и их расшифровка:
B33: ГОЗ – государственный оборонный заказ; НИР (ОКР) – научно-исследовательская работа (опытно-конструкторская работа).

Sheet 4д матер
AI1: Форма № 4д
A2: РАСШИФРОВКА
A3: затрат на приобретение сырья, материалов и вспомогательных материалов
E4: ТЕМА
A5: (наименование, шифр товара, работы, услуги)
A7: № п/п | B7: Наименование | C7: Код ОКП / ОКПД2 | D7: Код ЕКПС (при наличии) | E7: ФНН (при наличии) | F7: Единица измерения | G7: Отчетный период / период, предшествующий планируемому | R7: Стоимостная оценка затрат в условиях первого года производства | AA7: Планируемый период
G8: расход на единицу продукции | I8: цена за единицу измерения (руб.) | K8: затраты (руб.) | M8: обоснование цены поставки | O8: организация-поставщик (подрядчик, исполнитель) | R8: норма расхода (всего) на единицу продукции | S8: применяе-мый индекс цен | T8: цена за единицу измерения (руб.) | U8: затраты (руб.) | V8: обоснование цены поставки | X8: организация-поставщик (подрядчик, исполнитель) | AA8: первый год производства | AE8: n-ый год производства | AJ8: затраты (руб.)
G9: план | H9: факт | I9: план | J9: факт | K9: план | L9: факт | M9: первичные документы (номер и дата договора, протокола, счета, иное) | N9: метод определения цены | O9: наименование | Q9: ИНН | V9: обосновывающие документы | W9: метод определения цены | X9: наимено-вание | Y9: ИНН | AA9: норма расхода на единицу продукции | AB9: цена за единицу измерения (руб.) | AD9: затраты (руб.) | AE9: стоимостная оценка затрат n-го года в условиях первого года производства | AF9: норма расхода на единицу продукции | AG9: применяе-мый индекс цен | AH9: цена за единицу измерения (руб.) | AI9: затраты n-го года (руб.)
A10: 1 | B10: 2 | C10: 3 | D10: 4 | E10: 5 | F10: 6 | G10: 7 | H10: 8 | I10: 9 | J10: 10 | K10: 11 | L10: 12 | M10: 13.1 | N10: 13.2 | O10: 14 | Q10: 15 | R10: 16 | S10: 17 | T10: 18 | U10: 19 | V10: 20.1 | W10: 20.2 | X10: 21 | Y10: 22 | AA10: 23 | AB10: 24 | AD10: 25 | AE10: 26 | AF10: 27 | AG10: 28 | AH10: 29 | AI10: 30 | AJ10: 31
B11: ВСЕГО по разделу 1 и 2: | C11: - | D11: - | E11: - | F11: - | G11: - | H11: - | I11: - | J11: - | K11: - | L11: - | M11: - | N11: - | O11: - | Q11: - | R11: - | S11: - | T11: - | U11: - | V11: - | W11: - | X11: - | Y11: - | AA11: - | AB11: - | AD11: - | AE11: - | AF11: - | AG11: - | AH11: - | AI11: - | AJ11: -
A12: 1. | B12: Сырье и основные материалы: | C12: - | D12: - | E12: - | F12: - | G12: - | H12: - | I12: - | J12: - | K12: - | L12: - | M12: - | N12: - | O12: - | Q12: - | R12: - | S12: - | T12: - | U12: - | V12: - | W12: - | X12: - | Y12: - | AA12: - | AB12: - | AD12: - | AE12: - | AF12: - | AG12: - | AH12: - | AI12: - | AJ12: -
A13: 1.1 | B13: - | C13: - | D13: - | E13: - | F13: - | G13: - | H13: - | I13: - | J13: - | K13: - | L13: - | M13: - | N13: - | O13: - | Q13: - | R13: - | S13: - | T13: - | U13: - | V13: - | W13: - | X13: - | Y13: - | AA13: - | AB13: - | AD13: - | AE13: - | AF13: - | AG13: - | AH13: - | AI13: - | AJ13: -
B14: ИТОГО по разделу 1 | C14: - | D14: - | E14: - | F14: - | G14: - | H14: - | I14: - | J14: - | K14: - | L14: - | M14: - | N14: - | O14: - | Q14: - | R14: - | S14: - | T14: - | U14: - | V14: - | W14: - | X14: - | Y14: - | AA14: - | AB14: - | AD14: - | AE14: - | AF14: - | AG14: - | AH14: - | AI14: - | AJ14: -
A15: 2. | B15: Вспомогательные материалы: | C15: - | D15: - | E15: - | F15: - | G15: - | H15: - | I15: - | J15: - | K15: - | L15: - | M15: - | N15: - | O15: - | Q15: - | R15: - | S15: - | T15: - | U15: - | V15: - | W15: - | X15: - | Y15: - | AA15: - | AB15: - | AD15: - | AE15: - | AF15: - | AG15: - | AH15: - | AI15: - | AJ15: -
A16: 2.1 | B16: - | C16: - | D16: - | E16: - | F16: - | G16: - | H16: - | I16: - | J16: - | K16: - | L16: - | M16: - | N16: - | O16: - | Q16: - | R16: - | S16: - | T16: - | U16: - | V16: - | W16: - | X16: - | Y16: - | AA16: - | AB16: - | AD16: - | AE16: - | AF16: - | AG16: - | AH16: - | AI16: - | AJ16: -
B17: ИТОГО по разделу 2 | C17: - | D17: - | E17: - | F17: - | G17: - | H17: - | I17: - | J17: - | K17: - | L17: - | M17: - | N17: - | O17: - | Q17: - | R17: - | S17: - | T17: - | U17: - | V17: - | W17: - | X17: - | Y17: - | AA17: - | AB17: - | AD17: - | AE17: - | AF17: - | AG17: - | AH17: - | AI17: - | AJ17: -
B18: ВСЕГО по разделу 3: | C18: - | D18: - | E18: - | F18: - | G18: - | H18: - | I18: - | J18: - | K18: - | L18: - | M18: - | N18: - | O18: - | Q18: - | R18: - | S18: - | T18: - | U18: - | V18: - | W18: - | X18: - | Y18: - | AA18: - | AB18: - | AD18: - | AE18: - | AF18: - | AG18: - | AH18: - | AI18: - | AJ18: -
A19: 3. | B19: Возвратные отходы (вычитаются): | C19: - | D19: - | E19: - | F19: - | G19: - | H19: - | I19: - | J19: - | K19: - | L19: - | M19: - | N19: - | O19: - | Q19: - | R19: - | S19: - | T19: - | U19: - | V19: - | W19: - | X19: - | Y19: - | AA19: - | AB19: - | AD19: - | AE19: - | AF19: - | AG19: - | AH19: - | AI19: - | AJ19: -
A20: 3.1 | B20: - | C20: - | D20: - | E20: - | F20: - | G20: - | H20: - | I20: - | J20: - | K20: - | L20: - | M20: - | N20: - | O20: - | Q20: - | R20: - | S20: - | T20: - | U20: - | V20: - | W20: - | X20: - | Y20: - | AA20: - | AB20: - | AD20: - | AE20: - | AF20: - | AG20: - | AH20: - | AI20: - | AJ20: -
B23: Начальник ОФЭиАУ НИОКР | O23: Ответственный исполнитель | AE23: Руководитель договора
B24: _____________________ Н.О. Васецкая | O24: _____________________ И.О. Фамилия | AE24: _____________________ А.И. Боровков
B25: (подпись) (Ф.И.О.) | O25: (подпись) (Ф.И.О.) | AE25: (подпись) (Ф.И.О.)
B26: «____» __________________ 2025 г. | O26: «____» __________________ 2025 г. | AE26: «____» __________________ 2025 г.

Sheet 5д полуф
AI1: Форма № 5д
A2: РАСШИФРОВКА
A3: затрат на приобретение полуфабрикатов
F4: ТЕМА
A5: (наименование, шифр товара, работы, услуги)
A7: № п/п | B7: Наименование | C7: Код ОКП / ОКПД2 | D7: Код ЕКПС (при наличии) | E7: ФНН (при наличии) | F7: Единица измерения | G7: Отчетный период / период, предшествующий планируемому | R7: Стоимостная оценка затрат в условиях первого года производства | AA7: Планируемый период
G8: расход на единицу продукции | I8: цена за единицу измерения (руб.) | K8: затраты (руб.) | M8: обоснование цены поставки | O8: организация-поставщик (подрядчик, исполнитель) | R8: норма расхода (всего) на единицу продукции | S8: применяе-мый индекс цен | T8: цена за единицу измерения (руб.) | U8: затраты (руб.) | V8: обоснование цены поставки | X8: организация-поставщик (подрядчик, исполнитель) | AA8: первый год производства | AE8: n-ый год производства | AJ8: затраты (руб.)
G9: план | H9: факт | I9: план | J9: факт | K9: план | L9: факт | M9: первичные документы (номер и дата договора, протокола, счета, иное) | N9: метод определения цены | O9: наименование | Q9: ИНН | V9: обосновывающие документы | W9: метод определения цены | X9: наименование | Z9: ИНН | AA9: норма расхода на единицу продукции | AC9: цена за единицу измерения (руб.) | AD9: затраты (руб.) | AE9: стоимостная оценка затрат n-го года в условиях первого года производства | AF9: норма расхода на единицу продукции | AG9: применяе-мый индекс цен | AH9: цена за единицу измерения (руб.) | AI9: затраты n-го года (руб.)
A10: 1 | B10: 2 | C10: 3 | D10: 4 | E10: 5 | F10: 6 | G10: 7 | H10: 8 | I10: 9 | J10: 10 | K10: 11 | L10: 12 | M10: 13.1 | N10: 13.2 | O10: 14 | Q10: 15 | R10: 16 | S10: 17 | T10: 18 | U10: 19 | V10: 20.1 | W10: 20.2 | X10: 21 | Z10: 22 | AA10: 23 | AC10: 24 | AD10: 25 | AE10: 26 | AF10: 27 | AG10: 28 | AH10: 29 | AI10: 30 | AJ10: 31
B11: ВСЕГО: | C11: - | D11: - | E11: - | F11: - | G11: - | H11: - | I11: - | J11: - | K11: - | L11: - | M11: - | N11: - | O11: - | Q11: - | R11: - | S11: - | T11: - | U11: - | V11: - | W11: - | X11: - | Z11: - | AA11: - | AC11: - | AD11: - | AE11: - | AF11: - | AG11: - | AH11: - | AI11: - | AJ11: -
A12: 1. | B12: Покупные полуфабрикаты: | C12: - | D12: - | E12: - | F12: - | G12: - | H12: - | I12: - | J12: - | K12: - | L12: - | M12: - | N12: - | O12: - | Q12: - | R12: - | S12: - | T12: - | U12: - | V12: - | W12: - | X12: - | Z12: - | AA12: - | AC12: - | AD12: - | AE12: - | AF12: - | AG12: - | AH12: - | AI12: - | AJ12: -
A13: 1.1 | B13: - | C13: - | D13: - | E13: - | F13: - | G13: - | H13: - | I13: - | J13: - | K13: - | L13: - | M13: - | N13: - | O13: - | Q13: - | R13: - | S13: - | T13: - | U13: - | V13: - | W13: - | X13: - | Z13: - | AA13: - | AC13: - | AD13: - | AE13: - | AF13: - | AG13: - | AH13: - | AI13: - | AJ13: -
B14: ИТОГО по разделу 1 | C14: - | D14: - | E14: - | F14: - | G14: - | H14: - | I14: - | J14: - | K14: - | L14: - | M14: - | N14: - | O14: - | Q14: - | R14: - | S14: - | T14: - | U14: - | V14: - | W14: - | X14: - | Z14: - | AA14: - | AC14: - | AD14: - | AE14: - | AF14: - | AG14: - | AH14: - | AI14: - | AJ14: -
A15: 2. | B15: Возвратные отходы (вычитаются): | C15: - | D15: - | E15: - | F15: - | G15: - | H15: - | I15: - | J15: - | K15: - | L15: - | M15: - | N15: - | O15: - | Q15: - | R15: - | S15: - | T15: - | U15: - | V15: - | W15: - | X15: - | Z15: - | AA15: - | AC15: - | AD15: - | AE15: - | AF15: - | AG15: - | AH15: - | AI15: - | AJ15: -
A16: 2.1 | B16: - | C16: - | D16: - | E16: - | F16: - | G16: - | H16: - | I16: - | J16: - | K16: - | L16: - | M16: - | N16: - | O16: - | Q16: - | R16: - | S16: - | T16: - | U16: - | V16: - | W16: - | X16: - | Z16: - | AA16: - | AC16: - | AD16: - | AE16: - | AF16: - | AG16: - | AH16: - | AI16: - | AJ16: -
B17: ИТОГО по разделу 2 | C17: - | D17: - | E17: - | F17: - | G17: - | H17: - | I17: - | J17: - | K17: - | L17: - | M17: - | N17: - | O17: - | Q17: - | R17: - | S17: - | T17: - | U17: - | V17: - | W17: - | X17: - | Z17: - | AA17: - | AC17: - | AD17: - | AE17: - | AF17: - | AG17: - | AH17: - | AI17: - | AJ17: -
B20: Начальник ОФЭиАУ НИОКР | O20: Ответственный исполнитель | AC20: Руководитель договора
B21: _____________________ Н.О. Васецкая | O21: _____________________ И.О. Фамилия | AC21: _____________________ А.И. Боровков
B22: (подпись) (Ф.И.О.) | O22: (подпись) (Ф.И.О.) | AC22: (подпись) (Ф.И.О.)
B23: «____» __________________ 2025 г. | O23: «____» __________________ 2025 г. | AC23: «____» __________________ 2025 г.

Sheet 6д пки
AI1: Форма № 6д
A2: РАСШИФРОВКА
A3: затрат на приобретение комплектующих изделий
G4: ТЕМА
A5: (наименование, шифр товара, работы, услуги)
A7: № п/п | B7: Наименование | C7: Код ОКП / ОКПД2 | D7: Код ЕКПС (при наличии) | E7: ФНН (при наличии) | F7: Единица измерения | G7: Отчетный период / период, предшествующий планируемому | R7: Стоимостная оценка затрат в условиях первого года производства | AA7: Планируемый период
G8: расход на единицу продукции | I8: цена за единицу измерения (руб.) | K8: затраты (руб.) | M8: обоснование цены поставки | O8: организация-поставщик (подрядчик, исполнитель) | R8: норма расхода (всего) на единицу продукции | S8: применяе-мый индекс цен5 | T8: цена за единицу измерения (руб.) | U8: затраты (руб.) | V8: обоснование цены поставки | X8: организация-поставщик (подрядчик, исполнитель) | AA8: первый год производства | AE8: n-ый год производства | AJ8: затраты (руб.)
G9: план | H9: факт | I9: план | J9: факт | K9: план | L9: факт | M9: первичные документы (номер и дата договора, протокола, счета, иное) | N9: метод определения цены | O9: наименование | Q9: ИНН | V9: обосновывающие документы | W9: метод определения цены | X9: наименование | Z9: ИНН | AA9: норма расхода на единицу продукции | AB9: цена за единицу измерения (руб.) | AD9: затраты (руб.) | AE9: стоимостная оценка затрат n-го года в условиях первого года производства | AF9: норма расхода на единицу продукции | AG9: применяе-мый индекс цен | AH9: цена за единицу измерения (руб.) | AI9: затраты n-го года (руб.)
A10: 1 | B10: 2 | C10: 3 | D10: 4 | E10: 5 | F10: 6 | G10: 7 | H10: 8 | I10: 9 | J10: 10 | K10: 11 | L10: 12 | M10: 13.1 | N10: 13.2 | O10: 14 | Q10: 15 | R10: 16 | S10: 17 | T10: 18 | U10: 19 | V10: 20.1 | W10: 20.2 | X10: 21 | Z10: 22 | AA10: 23 | AB10: 24 | AD10: 25 | AE10: 26 | AF10: 27 | AG10: 28 | AH10: 29 | AI10: 30 | AJ10: 31
B11: Приобретение комплектующих изделий: | C11: - | D11: - | E11: - | F11: - | G11: - | H11: - | I11: - | J11: - | K11: - | L11: - | M11: - | N11: - | O11: - | Q11: - | R11: - | S11: - | T11: - | U11: - | V11: - | W11: - | X11: - | Z11: - | AA11: - | AB11: - | AD11: - | AE11: - | AF11: - | AG11: - | AH11: - | AI11: - | AJ11: -
B12: ИТОГО | C12: - | D12: - | E12: - | F12: - | G12: - | H12: - | I12: - | J12: - | K12: - | L12: - | M12: - | N12: - | O12: - | Q12: - | R12: - | S12: - | T12: - | U12: - | V12: - | W12: - | X12: - | Z12: - | AA12: - | AB12: - | AD12: - | AE12: - | AF12: - | AG12: - | AH12: - | AI12: - | AJ12: -
B14: Начальник ОФЭиАУ НИОКР | N14: Ответственный исполнитель | AA14: Руководитель договора
B15: _____________________ Н.О. Васецкая | N15: _____________________ И.О. Фамилия | AA15: _____________________ А.И. Боровков
B16: (подпись) (Ф.И.О.) | N16: (подпись) (Ф.И.О.) | AA16: (подпись) (Ф.И.О.)
B17: «____» __________________ 2025 г. | N17: «____» __________________ 2025 г. | AA17: «____» __________________ 2025 г.

Sheet 7(7д) работы(усл) НИР(ОКР)
I1: Форма № 7 (7д) НИР (ОКР)
B3: РАСШИФРОВКА затрат по работам (услугам), выполняемым (оказываемым) сторонними организациями,
B4: ТЕМА
A5: (наименование, шифр товара, работы, услуги)
A8: № п/п | B8: Наименование сторонних организаций | C8: Наименование работ (услуг) (шифр) | D8: Основание (ТТТ (ТТ), ТЗ (ТТЗ, ЧТЗ) на НИР (ОКР)) | E8: Сроки исполнения | F8: Цена работ (услуг) (руб.) | J8: Обоснование цены работ (услуг)
F9: всего | G9: в том числе:
G10: затраты (на __.__.____ г.) | I10: плановые затраты (с __.__.____ г. по __.__.____ г.) | J10: обосновывающие документы | K10: метод определения цены
G11: план | H11: факт
A12: 1 | B12: 2 | C12: 3 | D12: 4 | E12: 5 | F12: 6 | G12: 6.1.1 | H12: 6.1.2 | I12: 6.2 | J12: 7.1 | K12: 7.2
A13: 1. | B13: - | C13: - | D13: - | E13: - | F13: - | G13: - | H13: - | I13: - | J13: - | K13: -
A14: ИТОГО по этапу | C14: - | D14: - | E14: - | F14: - | G14: - | H14: - | I14: - | J14: - | K14: -
B16: Начальник ОФЭиАУ НИОКР | G16: Руководитель договора
B17: _____________________ Н.О. Васецкая | G17: _____________________ А.И. Боровков
B18: (подпись) (Ф.И.О.) | G18: (подпись) (Ф.И.О.)
B19: «____» __________________ 2025 г. | G19: «____» __________________ 2025 г.
A21: 1 В случае если технологический цикл производства продукции составляет более 1 года либо год начала производства продукции не соответствует году окончания ее производства и поставки (или завершения отдельных этапов поставки продукции, если государственным контрактом (контрактом) предусмотрены такие этапы), то организация представляет сведения по годам.
A22: 2 Заполняется для НИР (ОКР) (по каждому этапу (подэтапу), в отношении которого формируется стоимостной показатель).
A23: 3 Расчет цен на работы (услуги) исполнителей, выполняющих отдельные этапы (составные части) научно-исследовательских, опытно-конструкторских и других работ, представляется в объеме документов, предусмотренных пунктом 37 Положения о государственном регулировании цен на продукцию, поставляемую по государственному оборонному заказу, утвержденного постановлением Правительства Российской Федерации от 2 декабря 2017 года № 1465.
A24: 4 Графы заполняются в случае проведения процедуры перевода в фиксированную цену других видов цен на продукцию с учетом установленных в государственном контракте (контракте) условий уточнения и порядка перевода соответствующего вида цены на продукцию в фиксированную цену. Организацией с учетом установленных в государственном контракте (контракте) условий уточнения и порядка перевода соответствующего вида цены на продукцию в фиксированную цену в графе 6.1.1, 6.1.2 заполняются затраты по состоянию на конкретную дату, в графе 6.2 - планируемые затраты до окончания поставки продукции в рамках выполнения государственного контракта (контракта) (или завершения отдельных этапов поставки продукции, если государственным контрактом (контрактом) предусмотрены такие этапы), графа 6 представляет собой сумму граф 6.1.2 и 6.2. В случае если технологический цикл производства продукции составляет более 1 года либо год начала производства продукции не соответствует году окончания ее производства и поставки (или завершения отдельных этапов поставки продукции, если государственным контрактом (контрактом) предусмотрены такие этапы), то организация представляет сведения в графах 6, 6.1.1, 6.1.2 с разбивкой по годам.
A25: 5 Затраты на поставляемую продукцию включаются в цену продукции без учета НДС, за исключением случаев, когда продукция, на которую формируется цена, не подлежит налогообложению налогом на добавленную стоимость или организация не признается налогоплательщиком указанного налога в соответствии с Налоговым кодексом Российской Федерации. В таких случаях затраты указываются с учетом НДС и представляется соответствующее обоснование в пояснительной записке.
A27: Используемые сокращения и их расшифровка:
B28: ТТТ (ТТ) – тактико-технические требования (технические требования); ТТЗ (ТЗ) – тактико-техническое задание (техническое задание); ЧТЗ – частное техническое задание; НИР (ОКР) – научно-исследовательская работа (опытно-конструкторская работа).
G29: Ответственный исполнитель
G30: _____________________ И.О. Фамилия
G31: (подпись) (Ф.И.О.)
G32: «____» __________________ 2025 г.

Sheet 8 (8д) ТЗР
N1: Форма № 8 (8д)
B2: Расчет-обоснование норматива транспортно-заготовительных затрат
B3: ТЕМА
B4: (наименование, шифр товара, работы, услуги)
N5: (руб.)
A6: № п/п | B6: Вид транспортно-заготовительных затрат | C6: Отчетный период / период, предшествующий планируемому (год ____) | G6: Отчетный период / период, предшествующий планируемому (год ____) | K6: Планируемый период (год ____)
C7: всего транспортно-заготовительных затрат3 | D7: из транспортно-заготовительных затрат на: | G7: всего транспортно-заготовительных затрат | H7: из транспортно-заготовительных затрат на: | K7: всего транспортно-заготовительных затрат | L7: из транспортно-заготовительных затрат на:
D8: сырье и материалы | E8: покупные полуфабрикаты | F8: покупные комплектующие изделия | H8: сырье и материалы | I8: покупные полуфабрикаты | J8: покупные комплектующие изделия | L8: сырье и материалы | M8: покупные полуфабрикаты | N8: покупные комплектующие изделия
A9: 1 | B9: 2 | C9: 3 | D9: 4 | E9: 5 | F9: 6 | G9: 7 | H9: 8 | I9: 9 | J9: 10 | K9: 7 | L9: 8 | M9: 9 | N9: 10
A10: 1. | B10: - | C10: - | D10: - | E10: - | F10: - | G10: - | H10: - | I10: - | J10: - | K10: - | L10: - | M10: - | N10: -
B11: ИТОГО | C11: - | D11: - | E11: - | F11: - | G11: - | H11: - | I11: - | J11: - | K11: - | L11: - | M11: - | N11: -
B12: База распределения | C12: - | D12: - | E12: - | F12: - | G12: - | H12: - | I12: - | J12: - | K12: - | L12: - | M12: - | N12: -
B13: Отношение к базе распределения, % | C13: - | D13: - | E13: - | F13: - | G13: - | H13: - | I13: - | J13: - | K13: - | L13: - | M13: - | N13: -
B15: Начальник ОФЭиАУ НИОКР | H15: Руководитель договора
B16: _____________________ Н.О. Васецкая | H16: _____________________ А.И. Боровков
B17: (подпись) (Ф.И.О.) | H17: (подпись) (Ф.И.О.)
B18: «____» __________________ 2025 г. | H18: «____» __________________ 2025 г.
H21: Ответственный исполнитель
H22: _____________________ И.Б. Войнов
H23: (подпись) (Ф.И.О.)
H24: «____» __________________ 2025 г.

Sheet 11дОПР
M1: Форма № 11д
B3: Смета и расчет общепроизводственных затрат по ФГАОУ ВО "СПбПУ"
B4: ТЕМА
B5: (наименование, шифр товара, работы, услуги)
M6: (руб.)
A7: № п/п | B7: Наименование статей | C7: Отчетный период / период, предшествующий планируемому (год _____) | G7: Отчетный период / период, предшествующий планируемому (год ____) | K7: Планируемый период
C8: план | E8: факт | G8: план | I8: факт | K8: применяе-мый индекс цен | L8: год ____
C9: всего | D9: в том числе по госконтрактам (контрактам) ГОЗ | E9: всего | F9: в том числе по госконтрактам (контрактам) ГОЗ | G9: всего | H9: в том числе по госконтрактам (контрактам) ГОЗ | I9: всего | J9: в том числе по госконтрактам (контрактам) ГОЗ | L9: предложено организацией-поставщиком (подрядчиком, исполнителем)
L10: всего | M10: в том числе по госконтрактам (контрактам) ГОЗ
A11: 1 | B11: 2 | C11: 3 | D11: 4 | E11: 5 | F11: 6 | G11: 3 | H11: 4 | I11: 5 | J11: 6 | L11: 11 | M11: 12
A12: 1 | B12: Амортизация зданий, сооружений, производственного оборудования, транспортных средств (имущества) | C12: - | D12: - | E12: - | F12: - | G12: - | H12: - | I12: - | J12: - | K12: - | L12: - | M12: -
A13: ИТОГО | C13: - | D13: - | E13: - | F13: - | G13: - | H13: - | I13: - | J13: - | K13: - | L13: - | M13: -
A14: База распределения общепроизводственных затрат (______________________________________) | C14: - | D14: - | E14: - | F14: - | G14: - | H14: - | I14: - | J14: - | K14: - | L14: - | M14: -
A15: Отношение общепроизводственных затрат к базе распределения, % | C15: - | D15: - | E15: - | F15: - | G15: - | H15: - | I15: - | J15: - | K15: - | L15: - | M15: -
B17: Начальник ОФЭиАУ НИОКР | I17: Руководитель договора
B18: _____________________ Н.О. Васецкая | I18: _____________________ А.И. Боровков
B19: (подпись) (Ф.И.О.) | I19: (подпись) (Ф.И.О.)
B20: «____» __________________ 2025 г. | I20: «____» __________________ 2025 г.
I22: Ответственный исполнитель
I23: _____________________ И.О. Фамилия
I24: (подпись) (Ф.И.О.)
I25: «____» __________________ 2025 г.

Sheet 13д внепроизв. расх.
M1: Форма № 13д
B3: Смета и расчет коммерческих (внепроизводственных) затрат
B4: ТЕМА
B5: (наименование, шифр товара, работы, услуги)
M6: (руб.)
A7: № п/п | B7: Наименование статей | C7: Отчетный период / период, предшествующий планируемому (год ____) | G7: Отчетный период / период, предшествующий планируемому (год ____) | K7: Планируемый период
C8: план | E8: факт | G8: план | I8: факт | K8: применяе-мый индекс цен | L8: год _____
C9: всего | D9: в том числе по госконтрактам (контрактам) ГОЗ | E9: всего | F9: в том числе по госконтрактам (контрактам) ГОЗ | G9: всего | H9: в том числе по госконтрактам (контрактам) ГОЗ | I9: всего | J9: в том числе по госконтрактам (контрактам) ГОЗ | L9: предложено организацией-поставщиком (подрядчиком, исполнителем)
L10: всего | M10: в том числе по госконтрактам (контрактам) ГОЗ
A11: 1 | B11: 2 | C11: 3 | D11: 4 | E11: 5 | F11: 6 | G11: 3 | H11: 4 | I11: 5 | J11: 6 | K11: 7 | L11: 8 | M11: 9
A12: 1. | B12: - | C12: - | D12: - | E12: - | F12: - | G12: - | H12: - | I12: - | J12: - | K12: - | L12: - | M12: -
A13: ИТОГО | C13: - | D13: - | E13: - | F13: - | G13: - | H13: - | I13: - | J13: - | K13: - | L13: - | M13: -
A14: База распределения коммерческих (внепроизводственных) затрат (______________________________________) | C14: - | D14: - | E14: - | F14: - | G14: - | H14: - | I14: - | J14: - | K14: - | L14: - | M14: -
A15: Отношение коммерческих (внепроизводственных) затрат к базе распределения, % | C15: - | D15: - | E15: - | F15: - | G15: - | H15: - | I15: - | J15: - | K15: - | L15: - | M15: -
B18: Начальник ОФЭиАУ НИОКР | I18: Руководитель договора
B19: _____________________ Н.О. Васецкая | I19: _____________________ А.И. Боровков
B20: (подпись) (Ф.И.О.) | I20: (подпись) (Ф.И.О.)
B21: «____» __________________ 2025 г. | I21: «____» __________________ 2025 г.
I24: Ответственный исполнитель
I25: _____________________ И.О. Фамилия
I26: (подпись) (Ф.И.О.)
I27: «____» __________________ 2025 г.

Sheet 14д СЗ
K1: Форма № 14д
A2: РАСШИФРОВКА специальных затрат
B3: ТЕМА
B4: (наименование, шифр товара, работы, услуги)
A7: № п/п | B7: Наименование статей затрат | C7: Затраты отчетного периода / периода, предшествующего планируемому (руб.) | D7: Стоимостная оценка затрат в условиях первого года производства | F7: Основание для включения (техническая документация) | G7: Планируемый период
G8: затраты в первом году производства | H8: n-ый год производства | K8: итого сумма затрат за весь период производства
D9: применяемый индекс цен | E9: затраты (руб.) | H9: стоимостная оценка затрат n-ого года в условиях первого года производства (руб.) | I9: применяемый индекс цен | J9: затраты n-ого года производства (руб.)
A10: 1 | B10: 2 | C10: 3 | D10: 4 | E10: 5 | F10: 6 | G10: 7 | H10: 8 | I10: 9 | J10: 10 | K10: 11
A11: 1. | B11: - | C11: - | D11: - | E11: - | F11: - | G11: - | H11: - | I11: - | J11: - | K11: -
A12: ИТОГО | C12: - | D12: - | E12: - | F12: - | G12: - | H12: - | I12: - | J12: - | K12: -
A13: Количество изделий (комплектов и другое), штук | C13: - | D13: - | E13: - | F13: - | G13: - | H13: - | I13: - | J13: - | K13: -
A14: Затраты на единицу | C14: - | D14: - | E14: - | F14: - | G14: - | H14: - | I14: - | J14: - | K14: -
B16: Начальник ОФЭиАУ НИОКР | D16: Ответственный исполнитель | H16: Руководитель договора
B17: _____________________ Н.О. Васецкая | D17: _____________________ И.О. Фамилия | H17: _____________________ А.И. Боровков
B18: (подпись) (Ф.И.О.) | D18: (подпись) (Ф.И.О.) | H18: (подпись) (Ф.И.О.)
B19: «____» __________________ 2025 г. | D19: «____» __________________ 2025 г. | H19: «____» __________________ 2025 г.

Sheet  15 (15д) НИР(ОКР) Спецобор
M1: Форма № 15 (15д) НИР (ОКР)
A3: РАСШИФРОВКА затрат на специальное оборудование для научных (экспериментальных) работ
B4: ТЕМА
B5: (наименование, шифр товара, работы, услуги)
A7: № п/п | B7: Наименование специального оборудования | C7: Единица измерения | D7: Планируемый период (год ____) | K7: Обоснование цены поставки | M7: Планируемая организация-поставщик (подрядчик, исполнитель)
D8: количество | E8: цена за единицу измерения (руб.) | F8: транспортно-заготовительные затраты (%) | G8: стоимость (руб.) (гр.4*гр.5+гр.4*гр.5*гр.6) | H8: в том числе: | K8: обосновывающие документы | L8: метод определения цены | M8: наименование | O8: ИНН
H9: затраты (на __.__.____ г.) | J9: плановые затраты (с __.__.____ г. по __.__.____ г.)
H10: план | I10: факт
A11: 1 | B11: 2 | C11: 3 | D11: 4 | E11: 5 | F11: 6 | G11: 7 | H11: 7.1.1 | I11: 7.1.2 | J11: 7.2 | K11: 8.1 | L11: 8.2 | M11: 9 | O11: 10
A12: 1. | B12: Приобретаемое специальное оборудование | C12: - | D12: - | E12: - | F12: - | G12: - | H12: - | I12: - | J12: - | K12: - | L12: - | M12: - | O12: -
A13: 1.1 | B13: - | C13: - | D13: - | E13: - | F13: - | G13: - | H13: - | I13: - | J13: - | K13: - | L13: - | M13: - | O13: -
A14: 2. | B14: Специальное оборудование, изготавливаемое собственными силами | C14: - | D14: - | E14: - | F14: X | G14: - | H14: - | I14: - | J14: - | K14: X | L14: X | M14: X | O14: X
A15: 2.1 | B15: - | C15: - | D15: - | E15: - | F15: X | G15: - | H15: - | I15: - | J15: - | K15: X | L15: X | M15: X | O15: X
B16: ИТОГО по этапу (году) | C16: - | D16: - | E16: - | F16: - | G16: - | H16: - | I16: - | J16: - | K16: X | L16: X | M16: X | O16: X
B19: Начальник ОФЭиАУ НИОКР | F19: Ответственный исполнитель | K19: Руководитель договора
B20: _____________________ Н.О. Васецкая | F20: _____________________ И.О. Фамилия | K20: _____________________ А.И. Боровков
B21: (подпись) (Ф.И.О.) | F21: (подпись) (Ф.И.О.) | K21: (подпись) (Ф.И.О.)
B22: «____» __________________ 2025 г. | F22: «____» __________________ 2025 г. | K22: «____» __________________ 2025 г.

Sheet 16д спец. тех. оснастка
I1: Форма № 16д
B3: РАСШИФРОВКА
B4: затрат на специальную технологическую оснастку
B5: ТЕМА
A6: (наименование, шифр товара, работы, услуги)
A8: № п/п | B8: Наименование статей затрат | C8: Затраты отчетного периода / периода, предшествующего планируемому (год _____) (руб.) | D8: Стоимостная оценка затрат в условиях первого года производства (год ____) | F8: Планируемый период
F9: затраты в первом году производства (год _____) (руб.) | G9: n-ый год производства (год ____) | J9: итого затрат за весь период производства (руб.)
D10: применяемый индекс цен | E10: затраты (руб.) | G10: стоимостная оценка затрат n-ого года в условиях первого года производства (руб.) | H10: применяемый индекс цен | I10: затраты в n-ом году производства (руб.)
A11: 1 | B11: 2 | C11: 3 | D11: 4 | E11: 5 | F11: 6 | G11: 7 | H11: 8 | I11: 9 | J11: 10
B12: Затраты на специальную технологическую оснастку - всего: | C12: - | D12: - | E12: - | F12: - | G12: - | H12: - | I12: - | J12: -
B13: в том числе: | C13: - | D13: - | E13: - | F13: - | G13: - | H13: - | I13: - | J13: -
A14: 1. | B14: Остаточная стоимость оснастки по состоянию на __.___._____ | C14: - | D14: - | E14: - | F14: - | G14: - | H14: - | I14: - | J14: -
A15: 2. | B15: Стоимость приобретенной оснастки | C15: - | D15: - | E15: - | F15: - | G15: - | H15: - | I15: - | J15: -
A16: 3. | B16: Стоимость вновь изготовленной оснастки - всего: | C16: - | D16: - | E16: - | F16: - | G16: - | H16: - | I16: - | J16: -
B17: в том числе:
B18: материальные затраты | C18: - | D18: - | E18: - | F18: - | G18: - | H18: - | I18: - | J18: -
B19: трудоемкость (____________) | C19: - | D19: - | E19: - | F19: - | G19: - | H19: - | I19: - | J19: -
B20: затраты на оплату труда - всего: | C20: - | D20: - | E20: - | F20: - | G20: - | H20: - | I20: - | J20: -
B21: в том числе: | C21: - | D21: - | E21: - | F21: - | G21: - | H21: - | I21: - | J21: -
B22: - основная заработная плата | C22: - | D22: - | E22: - | F22: - | G22: - | H22: - | I22: - | J22: -
B23: - дополнительная заработная плата | C23: - | D23: - | E23: - | F23: - | G23: - | H23: - | I23: - | J23: -
B24: страховые взносы на обязательное социальное страхование | C24: - | D24: - | E24: - | F24: - | G24: - | H24: - | I24: - | J24: -
B25: общепроизводственные затраты | C25: - | D25: - | E25: - | F25: - | G25: - | H25: - | I25: - | J25: -
A26: 4. | B26: Стоимость ремонта и поддержания в рабочем состоянии оснастки - всего: | C26: - | D26: - | E26: - | F26: - | G26: - | H26: - | I26: - | J26: -
B27: в том числе: | C27: - | D27: - | E27: - | F27: - | G27: - | H27: - | I27: - | J27: -
B28: материальные затраты | C28: - | D28: - | E28: - | F28: - | G28: - | H28: - | I28: - | J28: -
B29: трудоемкость (____________) | C29: - | D29: - | E29: - | F29: - | G29: - | H29: - | I29: - | J29: -
B30: затраты на оплату труда - всего: | C30: - | D30: - | E30: - | F30: - | G30: - | H30: - | I30: - | J30: -
B31: в том числе: | C31: - | D31: - | E31: - | F31: - | G31: - | H31: - | I31: - | J31: -
B32: - основная заработная плата | C32: - | D32: - | E32: - | F32: - | G32: - | H32: - | I32: - | J32: -
B33: - дополнительная заработная плата | C33: - | D33: - | E33: - | F33: - | G33: - | H33: - | I33: - | J33: -
B34: страховые взносы на обязательное социальное страхование | C34: - | D34: - | E34: - | F34: - | G34: - | H34: - | I34: - | J34: -
B35: общепроизводственные затраты | C35: - | D35: - | E35: - | F35: - | G35: - | H35: - | I35: - | J35: -
B36: Количество изделий (комплектов и другое) с учетом периода использования, штук | C36: - | D36: - | E36: - | F36: - | G36: - | H36: - | I36: - | J36: -
B37: Затраты на единицу с учетом ставки погашения на единицу изделия | C37: - | D37: - | E37: - | F37: - | G37: - | H37: - | I37: - | J37: -
B39: Ставка погашения на единицу изделия | C39: -
B41: Начальник ОФЭиАУ НИОКР | C41: Ответственный исполнитель | G41: Руководитель договора
B42: _____________________ Н.О. Васецкая | C42: _____________________ И.О. Фамилия | G42: _____________________ А.И. Боровков
B43: (подпись) (Ф.И.О.) | C43: (подпись) (Ф.И.О.) | G43: (подпись) (Ф.И.О.)
B44: «____» __________________ 2025 г. | C44: «____» __________________ 2025 г. | G44: «____» __________________ 2025 г.

Sheet 17 (17д) осв пр-ва
N1: Форма № 17 (17д)
B2: РАСШИФРОВКА
B3: затрат на подготовку и освоение производства на ТЕМА
B4: (наименование, шифр товара, работы, услуги)
A6: № п/п | B6: Наименование статьи затрат | C6: Всего затрат (руб.) | D6: в том числе: | G6: Начало промышленной эксплуатации (дата) | H6: Нормативный срок освоения (месяцев, лет) | I6: Количество видов продукции | J6: Планируемый объем выпуска | L6: Норма погашения на единицу изделия (руб.) | M6: Погашено по состоянию на __.__.____ г. (руб.) | N6: Остаток к погашению (руб.) | O6: Примечание
D7: затраты (на __.__.____ г.) | F7: плановые затраты (с __.__.____ г. по __.__.____ г.) | J7: единица измерения | K7: количество
D8: план | E8: факт
A9: 1 | B9: 2 | C9: 3 | D9: 3.1.1 | E9: 3.1.2 | F9: 3.2 | G9: 4 | H9: 5 | I9: 6 | J9: 7 | K9: 8 | L9: 9 | M9: 10 | N9: 11 | O9: 12
A10: 1. | B10: Пусковые затраты, всего: | C10: - | D10: - | E10: - | F10: - | G10: - | H10: - | I10: - | J10: - | K10: - | L10: - | M10: - | N10: - | O10: -
B11: в том числе: | C11: - | D11: - | E11: - | F11: - | G11: - | H11: - | I11: - | J11: - | K11: - | L11: - | M11: - | N11: - | O11: -
B12: - | C12: - | D12: - | E12: - | F12: - | G12: - | H12: - | I12: - | J12: - | K12: - | L12: - | M12: - | N12: - | O12: -
A13: 2. | B13: Подготовка и освоение производства новых видов продукции, всего: | C13: - | D13: - | E13: - | F13: - | G13: - | H13: - | I13: - | J13: - | K13: - | L13: - | M13: - | N13: - | O13: -
B14: в том числе: | C14: - | D14: - | E14: - | F14: - | G14: - | H14: - | I14: - | J14: - | K14: - | L14: - | M14: - | N14: - | O14: -
A15: 2.1 | B15: Подготовка и освоение видов продукции, производство которой возобновляется после длительного перерыва (два календарных года и более), всего: | C15: - | D15: - | E15: - | F15: - | G15: - | H15: - | I15: - | J15: - | K15: - | L15: - | M15: - | N15: - | O15: -
B16: в том числе: | C16: - | D16: - | E16: - | F16: - | G16: - | H16: - | I16: - | J16: - | K16: - | L16: - | M16: - | N16: - | O16: -
B17: - | C17: - | D17: - | E17: - | F17: - | G17: - | H17: - | I17: - | J17: - | K17: - | L17: - | M17: - | N17: - | O17: -
A18: 2.2 | B18: Подготовка и освоение видов продукции, объемы производства которых увеличились в два и более раз, всего: | C18: - | D18: - | E18: - | F18: - | G18: - | H18: - | I18: - | J18: - | K18: - | L18: - | M18: - | N18: - | O18: -
B19: в том числе: | C19: - | D19: - | E19: - | F19: - | G19: - | H19: - | I19: - | J19: - | K19: - | L19: - | M19: - | N19: - | O19: -
B20: - | C20: - | D20: - | E20: - | F20: - | G20: - | H20: - | I20: - | J20: - | K20: - | L20: - | M20: - | N20: - | O20: -
A21: ИТОГО (строка 1 + строка 2) | C21: - | D21: - | E21: - | F21: - | G21: - | H21: - | I21: - | J21: - | K21: - | L21: - | M21: - | N21: - | O21: -
B23: Начальник ОФЭиАУ НИОКР | G23: Ответственный исполнитель | L23: Руководитель договора
B24: _____________________ Н.О. Васецкая | G24: _____________________ И.О. Фамилия | L24: _____________________ А.И. Боровков
B25: (подпись) (Ф.И.О.) | G25: (подпись) (Ф.И.О.) | L25: (подпись) (Ф.И.О.)
B26: «____» __________________ 2025 г. | G26: «____» __________________ 2025 г. | L26: «____» __________________ 2025 г.

Sheet 18 (18д) проч з
G1: Форма № 18 (18д)
A3: РАСШИФРОВКА прочих прямых затрат
A4: ТЕМА
A5: (наименование, шифр товара, работы, услуги)
A8: № статей | B8: Наименование статей затрат | C8: Затраты отчетного периода / периода, предшествующего планируемому (год _____) (руб.) | E8: Применяемый индекс цен | F8: Затраты планируемого периода (год _____) (руб.) | G8: Основания для включения затрат
C9: план | D9: факт
A10: 1 | B10: 2 | C10: 3.1 | D10: 3.2 | E10: 4 | F10: 5 | G10: 6
A11: 1 | B11: Затраты по обязательным видам страхования, возникающим при производстве продукции | C11: - | D11: - | E11: - | F11: - | G11: -
A12: ИТОГО | D12: - | E12: - | F12: - | G12: -
B14: Начальник ОФЭиАУ НИОКР | E14: Руководитель договора
B15: _____________________ Н.О. Васецкая | E15: _____________________ А.И. Боровков
B16: (подпись) (Ф.И.О.) | E16: (подпись) (Ф.И.О.)
B17: «____» __________________ 2026 г. | E17: «____» __________________ 2026 г.
E19: Ответственный исполнитель
E20: _____________________ И.О. Фамилия
E21: (подпись) (Ф.И.О.)
E22: «____» __________________ 2026 г.

Sheet 19 (19д) Командировки
P1: Форма № 19 (19д)
A3: Расчет затрат на командировки
B4: ТЕМА
E5: (наименование, шифр товара, работы, услуги)
A7: № п/п | B7: Пункт командировки | C7: Количество командируемых работников (чел.) | D7: Продолжительность пребывания в командировке одного работника (дней) | E7: Продолжительность пребывания в командировке командируемых работников (человеко-дни) | F7: Всего затрат (руб.) | G7: в том числе:
G8: суточные (руб.) | I8: средний заработок за дни нахождения в пути | L8: отчисления на обязательное социальное страхование (руб.) | M8: затраты по найму жилого помещения (руб.) | O8: проезд (в оба конца) (руб.) | Q8: другие расходы (руб.)
G9: в день | H9: всего | I9: средний заработок (руб.) | J9: количество дней в пути | K9: всего (руб.) | M9: в день | N9: всего | O9: стоимость проезда | P9: всего
A10: 1 | B10: 2 | C10: 3 | D10: 4 | E10: 5 | F10: 6 | G10: 7 | H10: 8 | I10: 9 | J10: 10 | K10: 11 | L10: 12 | M10: 13 | N10: 14 | O10: 15 | P10: 16 | Q10: 17
A11: 1. | B11: - | C11: - | D11: - | E11: - | F11: - | G11: - | H11: - | I11: - | J11: - | K11: - | L11: - | M11: - | N11: - | O11: - | P11: - | Q11: -
A12: ИТОГО суммарно по затратам | B12: отчетный период / период, предшествующий планируемому ( ____г.) | D12: - | E12: - | F12: - | G12: - | H12: - | I12: - | J12: - | K12: - | L12: - | M12: - | N12: - | O12: - | P12: - | Q12: -
B13: применяемый индекс цен | D13: X | E13: X | F13: - | G13: X | H13: - | I13: - | J13: X | K13: - | L13: - | M13: X | N13: - | O13: X | P13: - | Q13: -
B14: планируемый период ( ____г.) | D14: - | E14: - | F14: - | G14: - | H14: - | I14: - | J14: - | K14: - | L14: - | M14: - | N14: - | O14: - | P14: - | Q14: -
A16: Проректор по научной работе | D16: Начальник ОФЭиАУ НИОКР | H16: Ответственный исполнитель | M16: Руководитель договора
A17: _____________________ Ю.В. Фомин | D17: _____________________ Н.О. Васецкая | H17: _____________________ И.О. Фамилия | M17: _____________________ А.И. Боровков
A18: (подпись) (Ф.И.О.) | D18: (подпись) (Ф.И.О.) | H18: (подпись) (Ф.И.О.) | M18: (подпись) (Ф.И.О.)
A19: «____» __________________ 2026 г. | D19: «____» __________________ 2026 г. | H19: «____» __________________ 2026 г. | M19: «____» __________________ 2026 г.

Sheet 10 (10д) ДЗП
F1: Форма № 10 (10д)
A3: Расчет-обоснование уровня (%) дополнительной заработной платы основных работников
A4: ТЕМА
F6: (руб.)
A7: № п/п | B7: Наименование | C7: Период, предшествующий отчетному (2024г.) | D7: Отчетный период / период, предшествующий планируемому (2025 г.) | F7: Планируемый период (2026 г.)
C8: факт | D8: план | E8: факт | F8: план
A9: 1 | B9: 2 | C9: 3 | D9: 4.1 | E9: 4.2 | F9: 5
A10: 1. | B10: Основная заработная плата основных работников | C10: - | D10: - | E10: - | F10: ='9 (9д) ОЗП НИР(ОКР)'!H23
A11: 2. | B11: Дополнительная заработная плата основных работников, | C11: - | D11: - | E11: - | F11: =ROUND(F10*0.086866,2)
A12: 2.1 | B12: в % к основной заработной плате основных работников, % | C12: - | D12: - | E12: - | F12: ='22 (22д) свед. о норм_26'!D17
A14: Структура дополнительной заработной платы
F15: (руб.)
A16: № п/п | B16: Наименование выплат | C16: Период, предшествующий отчетному (2024г.) | D16: Отчетный период / период, предшествующий планируемому (2025 г.) | F16: Планируемый период (2026 г.)
C17: факт | D17: план | E17: факт | F17: план
A18: 1 | B18: 2 | C18: 3 | D18: 4.1 | E18: 4.2 | F18: 5
A19: 1. | B19: =B11 | C19: - | D19: =D11 | E19: - | F19: =F11
A20: ИТОГО | C20: - | D20: =D19 | E20: - | F20: =F11
B22: Начальник ОФЭиАУ НИОКР | D22: Руководитель договора
B23: _____________________ Н.О. Васецкая | D23: _____________________ А.И. Боровков
B24: (подпись) (Ф.И.О.) | D24: (подпись) (Ф.И.О.)
B25: «____» __________________ 2025 г. | D25: «____» __________________ 2025 г.
A27: 1 При наличии различных уровней дополнительной заработной платы основных работников для различных подразделений организации-потенциального поставщика (подрядчика, исполнителя) представляются расчеты-обоснования по каждому такому подразделению.
A28: 2 К основным работникам относятся основные производственные рабочие, инженерно-технические и другие категории работников, непосредственно участвующие в процессе производства продукции, согласно порядку определения состава затрат, включаемых в цену продукции, поставляемой в рамках государственного оборонного заказа, утвержденному в соответствии с постановлением Правительства Российской Федерации от 2 декабря 2017 года № 1465 "О государственном регулировании цен на продукцию, поставляемую по государственному оборонному заказу, а также о внесении изменений и признании утратившими силу некоторых актов Правительства Российской Федерации".
A29: 3 В случае если технологический цикл производства продукции составляет более 1 года либо год начала производства продукции не соответствует году окончания ее производства и поставки (или завершения отдельных этапов поставки продукции, если государственным контрактом (контрактом) предусмотрены такие этапы), то организация представляет сведения по годам.
A30: 4 В случае если этапы НИР (ОКР) выполняются в одном году, то формы, содержащие информацию о финансово-хозяйственной деятельности организации в целом (формы №№ 8 (8д), 10 (10д), 11 (11д), 12 (12д), 13 (13д), 21, 21д, 22 (22д), 23, 23д приложения № 5 к настоящему приказу), представляются единожды в составе соответствующего предложения о цене.
A31: 5 При проведении процедуры перевода в фиксированную цену других видов цен на продукцию организацией с учетом установленных в государственном контракте (контракте) условий уточнения и порядка перевода соответствующего вида цены на продукцию в фиксированную цену в графе 5 представляются планируемые затраты года окончания поставки продукции в рамках выполнения государственного контракта (контракта) (или завершения отдельных этапов поставки продукции, если государственным контрактом (контрактом) предусмотрены такие этапы). В случае если технологический цикл производства продукции составляет более 1 года либо год начала производства продукции не соответствует году окончания ее производства и поставки (или завершения отдельных этапов поставки продукции, если государственным контрактом (контрактом) предусмотрены такие этапы), то организация представляет сведения о затратах по годам, предшествующим году поставки продукции, в соответствии с графами 4.1-4.2 на каждый год производства продукции, дополнив форму после графы 4.2 графами, аналогичными по содержанию графам 4.1-4.2 соответственно (с последующей корректировкой нумерации граф), для указания информации.
A32: 6 Указываются выплаты, предусмотренные локальным нормативным актом организации или нормативным правовым актом Российской Федерации, а также представляется такой локальный нормативный акт или оформляется ссылка на конкретную структурную единицу нормативных правовых актов Российской Федерации, являющихся основанием указанных выплат за счет фонда дополнительной заработной платы из состава себестоимости организации; при удельном весе более 10 процентов представляется расшифровка выплат.
A34: Используемые сокращения и их расшифровка:
B35: ГОЗ – государственный оборонный заказ; НИР (ОКР) – научно-исследовательская работа (опытно-конструкторская работа).
B36: Начальник отдела труда и заработной платы | D36: Ответственный исполнитель
B37: _____________________ Ю.Г. Шадрина | D37: _____________________ И.Б. Войнов
B38: (подпись) (Ф.И.О.) | D38: (подпись) (Ф.И.О.)
B39: «____» __________________ 2025 г. | D39: «____» __________________ 2025 г.

Sheet Ф.12
GQ1: Форма № 12
A3: Смета и расчет
H4: общехозяйственных затрат/административно-управленческих расходов
E5: ТЕМА
GQ7: (руб.)
A8: № п/п | H8: Наименование статей | BJ8: Отчетный период/период, предшествующий планируемому (год | DW8: 2025 | ED8: ) | EL8: применяемый индекс цен | FD8: Планируемый период (год | GF8: 2026 | GM8: )
BJ9: план | CX9: факт | FD9: предложено организацией-поставщиком (подрядчиком, исполнителем)
BJ10: всего | CC10: в том числе по госконтрактам (контрактам) ГОЗ | CX10: всего | DQ10: в том числе по госконтрактам (контрактам) ГОЗ | FD10: всего | FW10: в том числе по госконтрактам (контрактам) ГОЗ
A11: 1 | H11: 2 | BJ11: 3 | CC11: 4 | CX11: 5 | DQ11: 6 | EL11: 7 | FD11: 8 | FW11: 9
A12: 1 | H12: Норматив на ОХР | BJ12: - | CC12: - | CX12: - | DQ12: - | EL12: - | FD12: =ROUND(FD14*FD16/100,2) | FW12: =FD12
A13: ИТОГО | BJ13: - | CC13: - | CX13: - | DQ13: - | EL13: - | FD13: =FD12 | FW13: =FD13
A14: База распределения общехозяйственных затрат/административно-управленческих расходов | BJ14: - | CC14: - | CX14: - | DQ14: - | EL14: - | FD14: ='9 (9д) ОЗП НИР(ОКР)'!H23 | FW14: =FD14
A15: ( | C15: основная заработная плата основных исполнителей | AT15: )
A16: Отношение общехозяйственных затрат/административно-управленческих расходов к базе распределения, % | BJ16: - | CC16: - | CX16: - | DQ16: - | EL16: - | FD16: ='22 (22д) свед. о норм_26'!D22 | FW16: ='22 (22д) свед. о норм_26'!D22
G18: Начальник ОФЭиАУ НИОКР | DP18: Руководитель договора
G19: _____________________ Н.О. Васецкая | DP19: _____________________ А.И. Боровков
G20: (подпись) (Ф.И.О.) | DP20: (подпись) (Ф.И.О.)
G21: «____» __________________ 2025 г. | DP21: «____» __________________ 2025 г.
G24: Главный бухглтер ФГАОУ ВО "СПбПУ" | DP24: Ответственный исполнитель
G25: _____________________ Н.В. Иванова | DP25: _____________________ И.Б. Войнов
G26: (подпись) (Ф.И.О.) | DP26: (подпись) (Ф.И.О.)
G27: «____» __________________ 2025 г. | DP27: «____» __________________ 2025 г.

Sheet Ф.23
GC1: Форма № 23
A3: Расчет (обоснование) трудоемкости ТЕМА
A5: № п/п | E5: Наименование товаров, работ, услуг 4 | X5: Отчетный период/период, предшествующий планируемому (год | CX5: 2025 | DC5: ) | EJ5: Планируемый период (год | FT5: 2026 | FY5: )
X7: план | CD7: факт
X8: технологическая трудоемкость единицы продукции | AG8: ) | AR8: (руб.) | AV8: годовой объем производства (штуки) | BE8: технологическая трудоемкость всего (гр. 3 * гр. 5) | BN8: основная заработная плата основных работников (гр. 4 * гр. 6) | CD8: технологическая трудоемкость единицы продукции | CM8: ) | CX8: (руб.) | DB8: годовой объем производства (штуки) | DK8: технологическая трудоемкость всего (гр. 8 * гр. 10) | DT8: основная заработная плата основных работников (гр. 9 * гр. 11) | EJ8: технологическая трудоемкость единицы продукции | ES8: ) | FD8: (руб.) | FH8: годовой объем производства (штуки) | FQ8: технологическая трудоемкость всего (гр. 13 * гр. 15) | FZ8: основная заработная плата основных работников (гр. 14 * гр. 16)
AM9: чел./мес. | CS9: чел./мес. | EY9: чел./мес.
AG10: чел./мес. | CM10: чел./мес. | ES10: чел./мес.
AM11: стоимость | CS11: стоимость | EY11: стоимость
AG12: ( | CM12: ( | ES12: (
A13: 1 | E13: 2 | X13: 3 | AM13: 4 | AV13: 5 | BE13: 6 | BN13: 7 | CD13: 8 | CS13: 9 | DB13: 10 | DK13: 11 | DT13: 12 | EJ13: 13 | EY13: 14 | FH13: 15 | FQ13: 16 | FZ13: 17
A14: 1 | E14: СЧ ОКР "Исследование, в том числе с использованием моделей аэродинамики и теплового режима решетчатых органов управления (аэродинамических рулей) в части расчетных исследований аэродинамики и теплового режима решетчатых органов управления в составе многоразовой первой ступени ракеты-носителя «Амур» на участках струйного и бесструйного торможения для различных режимов обтекания, расположения относительно плоскости угла атаки и с учетом интерференции с прилегающей поверхностью ступени" | X14: - | AM14: - | AV14: - | BE14: - | BN14: - | CD14: - | CS14: - | DB14: - | DK14: - | DT14: - | EJ14: ='9 (9д) ОЗП НИР(ОКР)'!F23 | EY14: ='9 (9д) ОЗП НИР(ОКР)'!G12 | FH14: 1 | FQ14: =EJ14 | FZ14: ='9 (9д) ОЗП НИР(ОКР)'!H12
A15: ИТОГО по ГОЗ | X15: - | AM15: - | AV15: - | BE15: - | BN15: - | CD15: - | CS15: - | DB15: - | DK15: - | DT15: - | EJ15: =EJ14 | EY15: =EY14 | FH15: =FH14 | FQ15: =FQ14 | FZ15: =FZ14
A16: 1 | E16: - | X16: - | AM16: - | AV16: - | BE16: - | BN16: - | CD16: - | CS16: - | DB16: - | DK16: - | DT16: - | EJ16: - | EY16: - | FH16: - | FQ16: - | FZ16: -
A17: ИТОГО прочая продукция | X17: - | AM17: - | AV17: - | BE17: - | BN17: - | CD17: - | CS17: - | DB17: - | DK17: - | DT17: - | EJ17: - | EY17: - | FH17: - | FQ17: - | FZ17: -
A18: ВСЕГО | X18: - | AM18: - | AV18: - | BE18: - | BN18: - | CD18: - | CS18: - | DB18: - | DK18: - | DT18: - | EJ18: =EJ15 | EY18: =EY15 | FH18: =FH15 | FQ18: =FQ15 | FZ18: =FZ15
D20: Проректор по научной работе | BI20: Начальник ОФЭиАУ НИОКР | EJ20: Руководитель договора
D22: _____________________ Ю.В. Фомин | BI22: _____________________ Н.О. Васецкая | EJ22: _________________ А.И. Боровков
D23: «____» __________________ 2025 г. | BI23: «____» __________________ 2025 г. | EJ23: «____» __________________ 2025 г.
EJ25: Ответственный исполнитель
EJ27: __________________ И.Б. Войнов
EJ28: «____» __________________ 2025 г.
